[{"num":0,"x":"128.5980476","y":"35.8596688","addr":"대구 중구 남산동 735-40","region":"중구","fid":1},{"num":1,"x":"128.5967568","y":"35.86416708","addr":"대구 중구 남산동 912-19","region":"중구","fid":1},{"num":2,"x":"128.5835169","y":"35.85812625","addr":"대구 중구 남산동 2508-3","region":"중구","fid":1},{"num":3,"x":"128.6120086","y":"35.87364389","addr":"대구 중구 동인동3가 367-20","region":"중구","fid":1},{"num":4,"x":"128.5851395","y":"35.87847465","addr":"대구 중구 태평로3가 251","region":"중구","fid":1},{"num":5,"x":"128.6150335","y":"35.86386141","addr":"대구 중구 삼덕동3가 377-1","region":"중구","fid":1},{"num":6,"x":"128.6131572","y":"35.87045863","addr":"대구 중구 동인동3가 192","region":"중구","fid":1},{"num":7,"x":"128.6112062","y":"35.87133116","addr":"대구 중구 동인동3가 412","region":"중구","fid":1},{"num":8,"x":"128.593815","y":"35.85986097","addr":"대구 중구 남산동 700-27","region":"중구","fid":1},{"num":9,"x":"128.5887127","y":"35.86218312","addr":"대구 중구 남산동 231-3","region":"중구","fid":1},{"num":10,"x":"128.6150081","y":"35.86591316","addr":"대구 중구 동인동4가 557","region":"중구","fid":1},{"num":11,"x":"128.5975458","y":"35.85763974","addr":"대구 중구 대봉동 590-437","region":"중구","fid":1},{"num":12,"x":"128.6010341","y":"35.86033032","addr":"대구 중구 봉산동 217-12","region":"중구","fid":1},{"num":13,"x":"128.6133887","y":"35.86619161","addr":"대구 중구 동인동4가 557","region":"중구","fid":1},{"num":14,"x":"128.6058636","y":"35.87075464","addr":"대구 중구 동인동1가 243","region":"중구","fid":1},{"num":15,"x":"128.5915813","y":"35.86026297","addr":"대구 중구 남산동 592-8","region":"중구","fid":1},{"num":16,"x":"128.6100918","y":"35.8692414","addr":"대구 중구 동인동4가 27","region":"중구","fid":1},{"num":17,"x":"128.6110743","y":"35.86617572","addr":"대구 중구 삼덕동3가 120-1","region":"중구","fid":1},{"num":18,"x":"128.6031541","y":"35.86669317","addr":"대구 중구 삼덕동2가 143-8","region":"중구","fid":1},{"num":19,"x":"128.6037632","y":"35.85559742","addr":"대구 중구 대봉동 174-3","region":"중구","fid":1},{"num":20,"x":"128.582217","y":"35.86287225","addr":"대구 중구 남산동 2991","region":"중구","fid":1},{"num":21,"x":"128.6093728","y":"35.87317411","addr":"대구 중구 동인동3가 271-117","region":"중구","fid":1},{"num":22,"x":"128.5922326","y":"35.8620031","addr":"대구 중구 남산동 616-37","region":"중구","fid":1},{"num":23,"x":"128.5773303","y":"35.86456679","addr":"대구 중구 대신동 1249","region":"중구","fid":1},{"num":24,"x":"128.5878397","y":"35.87789036","addr":"대구 중구 태평로3가 251","region":"중구","fid":1},{"num":25,"x":"128.5852304","y":"35.87596447","addr":"대구 중구 수창동 65-10","region":"중구","fid":1},{"num":26,"x":"128.592522","y":"35.86745605","addr":"대구 중구 계산동2가 153","region":"중구","fid":1},{"num":27,"x":"128.5842388","y":"35.87727866","addr":"대구 중구 달성동 339-1","region":"중구","fid":1},{"num":28,"x":"128.5811843","y":"35.86534607","addr":"대구 중구 대신동 2106","region":"중구","fid":1},{"num":29,"x":"128.5905548","y":"35.86455271","addr":"대구 중구 남산동 249-28","region":"중구","fid":1},{"num":30,"x":"128.5906274","y":"35.85861385","addr":"대구 중구 남산동 2114-15","region":"중구","fid":1},{"num":31,"x":"128.5989632","y":"35.86102593","addr":"대구 중구 봉산동 230-1","region":"중구","fid":1},{"num":32,"x":"128.7611791","y":"35.87577451","addr":"대구 동구 숙천동 234-6","region":"동구","fid":2},{"num":33,"x":"128.5950942","y":"35.87388597","addr":"대구 중구 북성로1가 51-1","region":"중구","fid":1},{"num":34,"x":"128.5957674","y":"35.85937905","addr":"대구 중구 남산동 719-16","region":"중구","fid":1},{"num":35,"x":"128.6433125","y":"35.90778853","addr":"대구 동구 불로동 602-6","region":"동구","fid":2},{"num":36,"x":"128.608759","y":"35.863368","addr":"대구 중구 삼덕동3가 346-8","region":"중구","fid":1},{"num":37,"x":"128.6067543","y":"35.85840792","addr":"대구 중구 대봉동 111-1","region":"중구","fid":1},{"num":38,"x":"128.634601","y":"35.98234646","addr":"대구 동구 중대동 1072","region":"동구","fid":2},{"num":39,"x":"128.6126836","y":"35.86716378","addr":"대구 중구 동인동4가 388","region":"중구","fid":1},{"num":40,"x":"128.6021871","y":"35.85948505","addr":"대구 중구 대봉동 719-17","region":"중구","fid":1},{"num":41,"x":"128.7559894","y":"35.87708333","addr":"대구 동구 숙천동 390","region":"동구","fid":2},{"num":42,"x":"128.5787697","y":"35.86400248","addr":"대구 중구 대신동 2110","region":"중구","fid":1},{"num":43,"x":"128.7569454","y":"35.88166636","addr":"대구 동구 숙천동 124","region":"동구","fid":2},{"num":44,"x":"128.5884746","y":"35.86488426","addr":"대구 중구 남산동 3016","region":"중구","fid":1},{"num":45,"x":"128.6045498","y":"35.87101157","addr":"대구 중구 동인동1가 402-2","region":"중구","fid":1},{"num":46,"x":"128.5847855","y":"35.86622591","addr":"대구 중구 대신동 832","region":"중구","fid":1},{"num":47,"x":"128.5845348","y":"35.86494032","addr":"대구 중구 대신동 868","region":"중구","fid":1},{"num":48,"x":"128.5861894","y":"35.86572217","addr":"대구 중구 동산동 715","region":"중구","fid":1},{"num":49,"x":"128.5860066","y":"35.86709336","addr":"대구 중구 동산동 575-1","region":"중구","fid":1},{"num":50,"x":"128.5861838","y":"35.86343362","addr":"대구 중구 남산동 122","region":"중구","fid":1},{"num":51,"x":"128.5858231","y":"35.86949721","addr":"대구 중구 동산동 194","region":"중구","fid":1},{"num":52,"x":"128.5876207","y":"35.86383822","addr":"대구 중구 남산동 130-2","region":"중구","fid":1},{"num":53,"x":"128.5838109","y":"35.86275036","addr":"대구 중구 남산동 2651-8","region":"중구","fid":1},{"num":54,"x":"128.5843251","y":"35.86853837","addr":"대구 중구 대신동 259-5","region":"중구","fid":1},{"num":55,"x":"128.5885193","y":"35.87131863","addr":"대구 중구 인교동 278-42","region":"중구","fid":1},{"num":56,"x":"128.5885072","y":"35.86771344","addr":"대구 중구 동산동 234","region":"중구","fid":1},{"num":57,"x":"128.5885463","y":"35.86041388","addr":"대구 중구 남산동 2200","region":"중구","fid":1},{"num":58,"x":"128.5873721","y":"35.8704409","addr":"대구 중구 동산동 127-1","region":"중구","fid":1},{"num":59,"x":"128.5840938","y":"35.86723417","addr":"대구 중구 대신동 277-1","region":"중구","fid":1},{"num":60,"x":"128.5885144","y":"35.85832825","addr":"대구 중구 남산동 2217-13","region":"중구","fid":1},{"num":61,"x":"128.5992297","y":"35.85975327","addr":"대구 중구 대봉동 743-4","region":"중구","fid":1},{"num":62,"x":"128.5989884","y":"35.87400558","addr":"대구 중구 용덕동 5-12","region":"중구","fid":1},{"num":63,"x":"128.5936525","y":"35.87289726","addr":"대구 중구 대안동 82-9","region":"중구","fid":1},{"num":64,"x":"128.5977079","y":"35.87228688","addr":"대구 중구 포정동 87","region":"중구","fid":1},{"num":65,"x":"128.5967967","y":"35.85995778","addr":"대구 중구 남산동 726-43","region":"중구","fid":1},{"num":66,"x":"128.5988897","y":"35.85785727","addr":"대구 중구 대봉동 590-41","region":"중구","fid":1},{"num":67,"x":"128.5991393","y":"35.87213723","addr":"대구 중구 동문동 41-1","region":"중구","fid":1},{"num":68,"x":"128.5938024","y":"35.8746362","addr":"대구 중구 태평로2가 29-4","region":"중구","fid":1},{"num":69,"x":"128.5969501","y":"35.87295779","addr":"대구 중구 향촌동 9-2","region":"중구","fid":1},{"num":70,"x":"128.5962642","y":"35.87427697","addr":"대구 중구 북성로1가 96-2","region":"중구","fid":1},{"num":71,"x":"128.5980547","y":"35.87336169","addr":"대구 중구 화전동 10","region":"중구","fid":1},{"num":72,"x":"128.5917905","y":"35.87245634","addr":"대구 중구 서문로1가 1-5","region":"중구","fid":1},{"num":73,"x":"128.5927497","y":"35.85935314","addr":"대구 중구 남산동 877","region":"중구","fid":1},{"num":74,"x":"128.5916239","y":"35.85894668","addr":"대구 중구 남산동 2175-12","region":"중구","fid":1},{"num":75,"x":"128.5916117","y":"35.85706158","addr":"대구 중구 남산동 2111-4","region":"중구","fid":1},{"num":76,"x":"128.5864235","y":"35.87174275","addr":"대구 중구 동산동 1-10","region":"중구","fid":1},{"num":77,"x":"128.599983","y":"35.87343528","addr":"대구 중구 교동 58-22","region":"중구","fid":1},{"num":78,"x":"128.5874439","y":"35.87179836","addr":"대구 중구 인교동 237-3","region":"중구","fid":1},{"num":79,"x":"128.5836529","y":"35.87194541","addr":"대구 중구 대신동 85","region":"중구","fid":1},{"num":80,"x":"128.585462","y":"35.87202039","addr":"대구 중구 시장북로 34-2","region":"중구","fid":1},{"num":81,"x":"128.7413876","y":"35.87213177","addr":"대구 동구 괴전동 228","region":"동구","fid":2},{"num":82,"x":"128.5865333","y":"35.86832718","addr":"대구 중구 동산동 206","region":"중구","fid":1},{"num":83,"x":"128.5910853","y":"35.87361795","addr":"대구 중구 북성로2가 19-4","region":"중구","fid":1},{"num":84,"x":"128.5972284","y":"35.87490442","addr":"대구 중구 태평로2가 2-2","region":"중구","fid":1},{"num":85,"x":"128.5923232","y":"35.87330834","addr":"대구 중구 북내동 19-2","region":"중구","fid":1},{"num":86,"x":"128.5839572","y":"35.87097519","addr":"대구 중구 대신동 151","region":"중구","fid":1},{"num":87,"x":"128.5981887","y":"35.86172735","addr":"대구 중구 대봉동 749","region":"중구","fid":1},{"num":88,"x":"128.5871482","y":"35.86477489","addr":"대구 중구 남산동 3016","region":"중구","fid":1},{"num":89,"x":"128.5848816","y":"35.86374234","addr":"대구 중구 남산동 97-1","region":"중구","fid":1},{"num":90,"x":"128.5847427","y":"35.86951176","addr":"대구 중구 대신동 115-38","region":"중구","fid":1},{"num":91,"x":"128.5852641","y":"35.87083212","addr":"대구 중구 동산동 50","region":"중구","fid":1},{"num":92,"x":"128.7379487","y":"35.87105005","addr":"대구 동구 괴전동 189-1","region":"동구","fid":2},{"num":93,"x":"128.5952939","y":"35.86490138","addr":"대구 중구 남산동 929-19","region":"중구","fid":1},{"num":94,"x":"128.5895552","y":"35.86724705","addr":"대구 중구 동산동 294","region":"중구","fid":1},{"num":95,"x":"128.5895044","y":"35.86332762","addr":"대구 중구 남산동 228-3","region":"중구","fid":1},{"num":96,"x":"128.5885762","y":"35.85702657","addr":"대구 중구 남산동 2118-2","region":"중구","fid":1},{"num":97,"x":"128.5855628","y":"35.86155993","addr":"대구 중구 남산동 2439-25","region":"중구","fid":1},{"num":98,"x":"128.6021266","y":"35.85753801","addr":"대구 중구 대봉동 760","region":"중구","fid":1},{"num":99,"x":"128.6043804","y":"35.86516834","addr":"대구 중구 삼덕동2가 149-1","region":"중구","fid":1},{"num":100,"x":"128.5968224","y":"35.86830484","addr":"대구 중구 남일동 20-1","region":"중구","fid":1},{"num":101,"x":"128.6139175","y":"35.87217709","addr":"대구 중구 동인동3가 315-7","region":"중구","fid":1},{"num":102,"x":"128.6058493","y":"35.86972305","addr":"대구 중구 동인동2가 74-15","region":"중구","fid":1},{"num":103,"x":"128.602292","y":"35.86802608","addr":"대구 중구 삼덕동1가 65-6","region":"중구","fid":1},{"num":104,"x":"128.6065266","y":"35.8557458","addr":"대구 중구 대봉동 122-2","region":"중구","fid":1},{"num":105,"x":"128.5966366","y":"35.86623102","addr":"대구 중구 덕산동 297-18","region":"중구","fid":1},{"num":106,"x":"128.5820808","y":"35.87647727","addr":"대구 중구 달성동 349-43","region":"중구","fid":1},{"num":107,"x":"128.6143485","y":"35.86967923","addr":"대구 중구 동인동3가 412","region":"중구","fid":1},{"num":108,"x":"128.6157281","y":"35.8672033","addr":"대구 중구 동인동4가 492","region":"중구","fid":1},{"num":109,"x":"128.6134025","y":"35.86494578","addr":"대구 중구 삼덕동3가 188-4","region":"중구","fid":1},{"num":110,"x":"128.5818025","y":"35.85857402","addr":"대구 중구 남산동 2321","region":"중구","fid":1},{"num":111,"x":"128.5967149","y":"35.8620496","addr":"대구 중구 남산동 679-8","region":"중구","fid":1},{"num":112,"x":"128.5907301","y":"35.86319724","addr":"대구 중구 남산동 576-15","region":"중구","fid":1},{"num":113,"x":"128.577876","y":"35.86316205","addr":"대구 중구 대신동 1450-1","region":"중구","fid":1},{"num":114,"x":"128.602991","y":"35.86493846","addr":"대구 중구 삼덕동2가 149-128","region":"중구","fid":1},{"num":115,"x":"128.6077041","y":"35.86842024","addr":"대구 중구 동인동2가 101","region":"중구","fid":1},{"num":116,"x":"128.5821047","y":"35.86043428","addr":"대구 중구 남산동 2482-1","region":"중구","fid":1},{"num":117,"x":"128.5922229","y":"35.8653986","addr":"대구 중구 남산동 473-2","region":"중구","fid":1},{"num":118,"x":"128.5938578","y":"35.8629556","addr":"대구 중구 남산동 648-3","region":"중구","fid":1},{"num":119,"x":"128.6029556","y":"35.87052676","addr":"대구 중구 동인동2가 259","region":"중구","fid":1},{"num":120,"x":"128.6028652","y":"35.87336456","addr":"대구 중구 교동 26-14","region":"중구","fid":1},{"num":121,"x":"128.6028392","y":"35.85849711","addr":"대구 중구 대봉동 760","region":"중구","fid":1},{"num":122,"x":"128.6028226","y":"35.85677114","addr":"대구 중구 대봉동 169-11","region":"중구","fid":1},{"num":123,"x":"128.5833728","y":"35.87513051","addr":"대구 중구 달성동 219-44","region":"중구","fid":1},{"num":124,"x":"128.6134227","y":"35.86918561","addr":"대구 중구 동인동4가 456-3","region":"중구","fid":1},{"num":125,"x":"128.607645","y":"35.87150638","addr":"대구 중구 동인동1가 333-4","region":"중구","fid":1},{"num":126,"x":"128.5897486","y":"35.87505292","addr":"대구 중구 수창동 46-1","region":"중구","fid":1},{"num":127,"x":"128.5925885","y":"35.87495628","addr":"대구 중구 수창동 30-25","region":"중구","fid":1},{"num":128,"x":"128.5878517","y":"35.87501218","addr":"대구 중구 수창동 50-19","region":"중구","fid":1},{"num":129,"x":"128.5845837","y":"35.87497054","addr":"대구 중구 달성동 339-1","region":"중구","fid":1},{"num":130,"x":"128.5779129","y":"35.86550728","addr":"대구 중구 대신동 1632","region":"중구","fid":1},{"num":131,"x":"128.5778256","y":"35.86170981","addr":"대구 중구 남산동 2951-1","region":"중구","fid":1},{"num":132,"x":"128.6099282","y":"35.86746173","addr":"대구 중구 동인동4가 220","region":"중구","fid":1},{"num":133,"x":"128.6107211","y":"35.86364941","addr":"대구 중구 삼덕동3가 316","region":"중구","fid":1},{"num":134,"x":"128.606779","y":"35.85709972","addr":"대구 중구 대봉동 111-1","region":"중구","fid":1},{"num":135,"x":"128.6054788","y":"35.85833299","addr":"대구 중구 대봉동 111-1","region":"중구","fid":1},{"num":136,"x":"128.6055654","y":"35.86220814","addr":"대구 중구 대봉동 654-1","region":"중구","fid":1},{"num":137,"x":"128.604378","y":"35.86025575","addr":"대구 중구 대봉동 55-50","region":"중구","fid":1},{"num":138,"x":"128.607563","y":"35.86492992","addr":"대구 중구 삼덕동2가 227","region":"중구","fid":1},{"num":139,"x":"128.6090004","y":"35.87187137","addr":"대구 중구 동인동3가 266-1","region":"중구","fid":1},{"num":140,"x":"128.6052707","y":"35.87307052","addr":"대구 중구 동인동1가 198-7","region":"중구","fid":1},{"num":141,"x":"128.6034481","y":"35.87187391","addr":"대구 중구 동인동1가 21-1","region":"중구","fid":1},{"num":142,"x":"128.6081693","y":"35.86930748","addr":"대구 중구 동인동2가 154-2","region":"중구","fid":1},{"num":143,"x":"128.6043685","y":"35.8639108","addr":"대구 중구 삼덕동2가 188-1","region":"중구","fid":1},{"num":144,"x":"128.6029909","y":"35.86155099","addr":"대구 중구 대봉동 60-10","region":"중구","fid":1},{"num":145,"x":"128.5945768","y":"35.86128845","addr":"대구 중구 남산동 698-22","region":"중구","fid":1},{"num":146,"x":"128.6006039","y":"35.85936558","addr":"대구 중구 대봉동 740-8","region":"중구","fid":1},{"num":147,"x":"128.5811397","y":"35.8673676","addr":"대구 중구 대신동 270-35","region":"중구","fid":1},{"num":148,"x":"128.5814123","y":"35.8790467","addr":"대구 중구 달성동 148-14","region":"중구","fid":1},{"num":149,"x":"128.595931","y":"35.86057695","addr":"대구 중구 남산동 693-22","region":"중구","fid":1},{"num":150,"x":"128.5945428","y":"35.85731345","addr":"대구 중구 남산동 2107-14","region":"중구","fid":1},{"num":151,"x":"128.582198","y":"35.86762358","addr":"대구 중구 대신동 826-9","region":"중구","fid":1},{"num":152,"x":"128.5980384","y":"35.86829492","addr":"대구 중구 삼덕동1가 4-7","region":"중구","fid":1},{"num":153,"x":"128.5901997","y":"35.8691725","addr":"대구 중구 남성로 158-1","region":"중구","fid":1},{"num":154,"x":"128.5893298","y":"35.87038012","addr":"대구 중구 서문로2가 84","region":"중구","fid":1},{"num":155,"x":"128.5987239","y":"35.86480283","addr":"대구 중구 봉산동 131-5","region":"중구","fid":1},{"num":156,"x":"128.6009968","y":"35.86252095","addr":"대구 중구 봉산동 168-19","region":"중구","fid":1},{"num":157,"x":"128.5976696","y":"35.86599704","addr":"대구 중구 봉산동 35-79","region":"중구","fid":1},{"num":158,"x":"128.5957105","y":"35.87048893","addr":"대구 중구 남일동 29-3","region":"중구","fid":1},{"num":159,"x":"128.6003341","y":"35.87194668","addr":"대구 중구 동문동 40","region":"중구","fid":1},{"num":160,"x":"128.599839","y":"35.86950803","addr":"대구 중구 공평동 15","region":"중구","fid":1},{"num":161,"x":"128.5857201","y":"35.87362306","addr":"대구 중구 인교동 83","region":"중구","fid":1},{"num":162,"x":"128.6000774","y":"35.86760829","addr":"대구 중구 삼덕동1가 18-23","region":"중구","fid":1},{"num":163,"x":"128.6115124","y":"35.86439368","addr":"대구 중구 삼덕동3가 231","region":"중구","fid":1},{"num":164,"x":"128.611035","y":"35.86778041","addr":"대구 중구 동인동4가 322-6","region":"중구","fid":1},{"num":165,"x":"128.6107043","y":"35.86524239","addr":"대구 중구 삼덕동3가 379","region":"중구","fid":1},{"num":166,"x":"128.6047872","y":"35.86638264","addr":"대구 중구 삼덕동2가 111-1","region":"중구","fid":1},{"num":167,"x":"128.5944089","y":"35.87645512","addr":"대구 중구 태평로2가 38-7","region":"중구","fid":1},{"num":168,"x":"128.5801595","y":"35.85964371","addr":"대구 중구 남산동 2612-101","region":"중구","fid":1},{"num":169,"x":"128.5987235","y":"35.86651218","addr":"대구 중구 봉산동 20-1","region":"중구","fid":1},{"num":170,"x":"128.5792008","y":"35.87393726","addr":"대구 중구 달성동 294-1","region":"중구","fid":1},{"num":171,"x":"128.6118461","y":"35.87248707","addr":"대구 중구 동인동3가 343","region":"중구","fid":1},{"num":172,"x":"128.610498","y":"35.87233082","addr":"대구 중구 동인동3가 271-48","region":"중구","fid":1},{"num":173,"x":"128.606108","y":"35.8665057","addr":"대구 중구 삼덕동2가 43","region":"중구","fid":1},{"num":174,"x":"128.6071231","y":"35.8605655","addr":"대구 중구 대봉동 28-55","region":"중구","fid":1},{"num":175,"x":"128.6083336","y":"35.85863518","addr":"대구 중구 대봉동 37-4","region":"중구","fid":1},{"num":176,"x":"128.6094344","y":"35.86434709","addr":"대구 중구 삼덕동3가 261-2","region":"중구","fid":1},{"num":177,"x":"128.6087747","y":"35.85997827","addr":"대구 중구 대봉동 31-28","region":"중구","fid":1},{"num":178,"x":"128.6085292","y":"35.85625775","addr":"대구 중구 대봉동 121-409","region":"중구","fid":1},{"num":179,"x":"128.6067528","y":"35.86420393","addr":"대구 중구 삼덕동2가 327","region":"중구","fid":1},{"num":180,"x":"128.604063","y":"35.86292615","addr":"대구 중구 대봉동 60-18","region":"중구","fid":1},{"num":181,"x":"128.6057781","y":"35.86841484","addr":"대구 중구 동인동2가 42","region":"중구","fid":1},{"num":182,"x":"128.5863278","y":"35.87504082","addr":"대구 중구 수창동 64-2","region":"중구","fid":1},{"num":183,"x":"128.5996178","y":"35.85700969","addr":"대구 중구 대봉동 590-346","region":"중구","fid":1},{"num":184,"x":"128.5829551","y":"35.87705155","addr":"대구 중구 달성동 110-5","region":"중구","fid":1},{"num":185,"x":"128.5815844","y":"35.87751252","addr":"대구 중구 달성동 349-41","region":"중구","fid":1},{"num":186,"x":"128.5801886","y":"35.87557386","addr":"대구 중구 달성동 294-1","region":"중구","fid":1},{"num":187,"x":"128.5869848","y":"35.87595807","addr":"대구 중구 수창동 174","region":"중구","fid":1},{"num":188,"x":"128.5862629","y":"35.87692541","addr":"대구 중구 도원동 3-5","region":"중구","fid":1},{"num":189,"x":"128.5910379","y":"35.87576265","addr":"대구 중구 태평로3가 221-7","region":"중구","fid":1},{"num":190,"x":"128.5892235","y":"35.8771058","addr":"대구 중구 태평로3가 206-6","region":"중구","fid":1},{"num":191,"x":"128.5950172","y":"35.87540908","addr":"대구 중구 태평로2가 33-2","region":"중구","fid":1},{"num":192,"x":"128.5966201","y":"35.87587426","addr":"대구 중구 태평로2가 1-1","region":"중구","fid":1},{"num":193,"x":"128.5987474","y":"35.87524827","addr":"대구 중구 태평로1가 1-216","region":"중구","fid":1},{"num":194,"x":"128.5897938","y":"35.87614985","addr":"대구 중구 수창동 173","region":"중구","fid":1},{"num":195,"x":"128.5920282","y":"35.86858269","addr":"대구 중구 수동 85","region":"중구","fid":1},{"num":196,"x":"128.5931282","y":"35.86935387","addr":"대구 중구 장관동 6","region":"중구","fid":1},{"num":197,"x":"128.594525","y":"35.86849411","addr":"대구 중구 종로2가 100-3","region":"중구","fid":1},{"num":198,"x":"128.5800751","y":"35.86454904","addr":"대구 중구 대신동 2106","region":"중구","fid":1},{"num":199,"x":"128.5921493","y":"35.87655194","addr":"대구 중구 태평로3가 214-15","region":"중구","fid":1},{"num":200,"x":"128.5854442","y":"35.85709178","addr":"대구 중구 남산동 2387-8","region":"중구","fid":1},{"num":201,"x":"128.5952567","y":"35.8673126","addr":"대구 중구 동성로3가 36-3","region":"중구","fid":1},{"num":202,"x":"128.637467","y":"35.913163","addr":"대구 동구 불로동 57-3","region":"동구","fid":2},{"num":203,"x":"128.5822673","y":"35.87849137","addr":"대구 중구 달성동 118-3","region":"중구","fid":1},{"num":204,"x":"128.5789093","y":"35.86117666","addr":"대구 중구 남산동 2951-1","region":"중구","fid":1},{"num":205,"x":"128.5801684","y":"35.86085824","addr":"대구 중구 남산동 2633-2","region":"중구","fid":1},{"num":206,"x":"128.6101794","y":"35.8707482","addr":"대구 중구 동인동3가 41-2","region":"중구","fid":1},{"num":207,"x":"128.5835307","y":"35.87847225","addr":"대구 중구 태평로3가 247-3","region":"중구","fid":1},{"num":208,"x":"128.5812856","y":"35.85955174","addr":"대구 중구 남산동 2621-2","region":"중구","fid":1},{"num":209,"x":"128.5812954","y":"35.86140874","addr":"대구 중구 남산동 2636-33","region":"중구","fid":1},{"num":210,"x":"128.5935956","y":"35.87562897","addr":"대구 중구 태평로3가 247","region":"중구","fid":1},{"num":211,"x":"128.581064","y":"35.86408025","addr":"대구 중구 대신동 2106","region":"중구","fid":1},{"num":212,"x":"128.5858767","y":"35.86060443","addr":"대구 중구 남산동 2442-4","region":"중구","fid":1},{"num":213,"x":"128.5988537","y":"35.86321376","addr":"대구 중구 봉산동 125","region":"중구","fid":1},{"num":214,"x":"128.6378505","y":"35.91174903","addr":"대구 동구 불로동 244-12","region":"동구","fid":2},{"num":215,"x":"128.5941091","y":"35.86750753","addr":"대구 중구 남성로 79","region":"중구","fid":1},{"num":216,"x":"128.5976329","y":"35.86496679","addr":"대구 중구 봉산동 46-1","region":"중구","fid":1},{"num":217,"x":"128.5869874","y":"35.86176489","addr":"대구 중구 남산동 190-1","region":"중구","fid":1},{"num":218,"x":"128.5863686","y":"35.85655937","addr":"대구 중구 남산동 2121-3","region":"중구","fid":1},{"num":219,"x":"128.5840396","y":"35.86072215","addr":"대구 중구 남산동 2466-1","region":"중구","fid":1},{"num":220,"x":"128.5792113","y":"35.86559684","addr":"대구 중구 대신동 2106","region":"중구","fid":1},{"num":221,"x":"128.5928701","y":"35.857252","addr":"대구 중구 남산동 2321","region":"중구","fid":1},{"num":222,"x":"128.5905395","y":"35.87208766","addr":"대구 중구 서성로1가 44","region":"중구","fid":1},{"num":223,"x":"128.5913297","y":"35.86127115","addr":"대구 중구 남산동 584-13","region":"중구","fid":1},{"num":224,"x":"128.5979557","y":"35.86935168","addr":"대구 중구 동성로2가 187-1","region":"중구","fid":1},{"num":225,"x":"128.5969307","y":"35.86720523","addr":"대구 중구 동성로3가 91-11","region":"중구","fid":1},{"num":226,"x":"128.5948628","y":"35.87104154","addr":"대구 중구 전동 23-2","region":"중구","fid":1},{"num":227,"x":"128.5923087","y":"35.87144243","addr":"대구 중구 서문로1가 10-1","region":"중구","fid":1},{"num":228,"x":"128.5999942","y":"35.86340642","addr":"대구 중구 봉산동 136-39","region":"중구","fid":1},{"num":229,"x":"128.6000587","y":"35.85838832","addr":"대구 중구 대봉동 738-1","region":"중구","fid":1},{"num":230,"x":"128.5999558","y":"35.86451458","addr":"대구 중구 봉산동 159-3","region":"중구","fid":1},{"num":231,"x":"128.5916481","y":"35.8642308","addr":"대구 중구 남산동 572-26","region":"중구","fid":1},{"num":232,"x":"128.5944149","y":"35.86428248","addr":"대구 중구 남산동 940-15","region":"중구","fid":1},{"num":233,"x":"128.5957564","y":"35.86289785","addr":"대구 중구 남산동 673-2","region":"중구","fid":1},{"num":234,"x":"128.5929515","y":"35.86115572","addr":"대구 중구 남산동 609-1","region":"중구","fid":1},{"num":235,"x":"128.6067657","y":"35.86191972","addr":"대구 중구 대봉동 19-29","region":"중구","fid":1},{"num":236,"x":"128.5945093","y":"35.85832346","addr":"대구 중구 남산동 714-2","region":"중구","fid":1},{"num":237,"x":"128.5951166","y":"35.87288186","addr":"대구 중구 대안동 14-3","region":"중구","fid":1},{"num":238,"x":"128.5914425","y":"35.87483076","addr":"대구 중구 수창동 40-1","region":"중구","fid":1},{"num":239,"x":"128.5906273","y":"35.87695951","addr":"대구 중구 태평로3가 247","region":"중구","fid":1},{"num":240,"x":"128.593269","y":"35.85832056","addr":"대구 중구 남산동 2109-4","region":"중구","fid":1},{"num":241,"x":"128.600612","y":"35.85723799","addr":"대구 중구 대봉동 731-7","region":"중구","fid":1},{"num":242,"x":"128.6074791","y":"35.86346735","addr":"대구 중구 삼덕동2가 285-3","region":"중구","fid":1},{"num":243,"x":"128.5871673","y":"35.86923411","addr":"대구 중구 동산동 206","region":"중구","fid":1},{"num":244,"x":"128.6051369","y":"35.85708448","addr":"대구 중구 대봉동 124-1","region":"중구","fid":1},{"num":245,"x":"128.5840551","y":"35.87369814","addr":"대구 중구 달성동 258-1","region":"중구","fid":1},{"num":246,"x":"128.5896533","y":"35.87293101","addr":"대구 중구 서야동 143","region":"중구","fid":1},{"num":247,"x":"128.6546345","y":"35.91194514","addr":"대구 동구 도동 145-1","region":"동구","fid":2},{"num":248,"x":"128.5914733","y":"35.87042797","addr":"대구 중구 수동 19-3","region":"중구","fid":1},{"num":249,"x":"128.6089283","y":"35.86548487","addr":"대구 중구 삼덕동3가 20","region":"중구","fid":1},{"num":250,"x":"128.6138433","y":"35.86807798","addr":"대구 중구 동인동4가 440-6","region":"중구","fid":1},{"num":251,"x":"128.5823817","y":"35.86875935","addr":"대구 중구 대신동 2105","region":"중구","fid":1},{"num":252,"x":"128.600242","y":"35.87520809","addr":"대구 중구 태평로1가 1-186","region":"중구","fid":1},{"num":253,"x":"128.5959671","y":"35.85721258","addr":"대구 중구 남산동 2321","region":"중구","fid":1},{"num":254,"x":"128.5934143","y":"35.86838427","addr":"대구 중구 장관동 30","region":"중구","fid":1},{"num":255,"x":"128.6661573","y":"35.9195765","addr":"대구 동구 도동 508-3","region":"동구","fid":2},{"num":256,"x":"128.5895079","y":"35.85897155","addr":"대구 중구 남산동 225-1","region":"중구","fid":1},{"num":257,"x":"128.6000748","y":"35.86594979","addr":"대구 중구 삼덕동1가 33-24","region":"중구","fid":1},{"num":258,"x":"128.6022566","y":"35.8725505","addr":"대구 중구 완전동 2-1","region":"중구","fid":1},{"num":259,"x":"128.6009913","y":"35.87093143","addr":"대구 중구 문화동 11-1","region":"중구","fid":1},{"num":260,"x":"128.607038","y":"35.85956035","addr":"대구 중구 대봉동 41-5","region":"중구","fid":1},{"num":261,"x":"128.6144733","y":"35.86724134","addr":"대구 중구 동인동4가 507-15","region":"중구","fid":1},{"num":262,"x":"128.6015598","y":"35.86477444","addr":"대구 중구 삼덕동1가 43-1","region":"중구","fid":1},{"num":263,"x":"128.6012267","y":"35.87368609","addr":"대구 중구 교동 49-34","region":"중구","fid":1},{"num":264,"x":"128.5858785","y":"35.85830311","addr":"대구 중구 남산동 2380-5","region":"중구","fid":1},{"num":265,"x":"128.6009755","y":"35.86702","addr":"대구 중구 삼덕동1가 26-3","region":"중구","fid":1},{"num":266,"x":"128.6042029","y":"35.85828432","addr":"대구 중구 대봉동 94-12","region":"중구","fid":1},{"num":267,"x":"128.6061783","y":"35.87176138","addr":"대구 중구 동인동1가 254-3","region":"중구","fid":1},{"num":268,"x":"128.614743","y":"35.86869582","addr":"대구 중구 동인동4가 474-2","region":"중구","fid":1},{"num":269,"x":"128.6493981","y":"35.9314265","addr":"대구 동구 봉무동 산 78-1","region":"동구","fid":2},{"num":270,"x":"128.5879968","y":"35.87322692","addr":"대구 중구 서야동 63","region":"중구","fid":1},{"num":271,"x":"128.5869178","y":"35.87392142","addr":"대구 중구 서야동 1-1","region":"중구","fid":1},{"num":272,"x":"128.604511","y":"35.86904225","addr":"대구 중구 동인동2가 42","region":"중구","fid":1},{"num":273,"x":"128.5891599","y":"35.86914936","addr":"대구 중구 계산동1가 103-1","region":"중구","fid":1},{"num":274,"x":"128.605726","y":"35.86474522","addr":"대구 중구 삼덕동2가 265-2","region":"중구","fid":1},{"num":275,"x":"128.6044939","y":"35.87221561","addr":"대구 중구 동인동1가 33-1","region":"중구","fid":1},{"num":276,"x":"128.6078284","y":"35.8622937","addr":"대구 중구 대봉동 13-17","region":"중구","fid":1},{"num":277,"x":"128.6082357","y":"35.86681033","addr":"대구 중구 삼덕동2가 50","region":"중구","fid":1},{"num":278,"x":"128.6119888","y":"35.86891995","addr":"대구 중구 동인동4가 335","region":"중구","fid":1},{"num":279,"x":"128.6104957","y":"35.86248979","addr":"대구 중구 삼덕동3가 376-25","region":"중구","fid":1},{"num":280,"x":"128.608233","y":"35.87059226","addr":"대구 중구 동인동1가 405-1","region":"중구","fid":1},{"num":281,"x":"128.6125611","y":"35.86405592","addr":"대구 중구 삼덕동3가 379","region":"중구","fid":1},{"num":282,"x":"128.6076345","y":"35.85580174","addr":"대구 중구 대봉동 121-365","region":"중구","fid":1},{"num":283,"x":"128.606939","y":"35.87077596","addr":"대구 중구 동인동1가 405-1","region":"중구","fid":1},{"num":284,"x":"128.6907236","y":"35.90837666","addr":"대구 동구 둔산동 산 33","region":"동구","fid":2},{"num":285,"x":"128.6041162","y":"35.85678224","addr":"대구 중구 대봉동 169-11","region":"중구","fid":1},{"num":286,"x":"128.6032351","y":"35.85966788","addr":"대구 중구 대봉동 88-61","region":"중구","fid":1},{"num":287,"x":"128.6049371","y":"35.85593995","addr":"대구 중구 대봉동 179-22","region":"중구","fid":1},{"num":288,"x":"128.6123757","y":"35.86611904","addr":"대구 중구 삼덕동3가 379","region":"중구","fid":1},{"num":289,"x":"128.6112461","y":"35.86980865","addr":"대구 중구 동인동3가 163","region":"중구","fid":1},{"num":290,"x":"128.6079502","y":"35.85727379","addr":"대구 중구 대봉동 121-306","region":"중구","fid":1},{"num":291,"x":"128.6097175","y":"35.86077572","addr":"대구 중구 대봉동 654-1","region":"중구","fid":1},{"num":292,"x":"128.608527","y":"35.86136528","addr":"대구 중구 대봉동 9-21","region":"중구","fid":1},{"num":293,"x":"128.599091","y":"35.87019113","addr":"대구 중구 동성로2가 66-1","region":"중구","fid":1},{"num":294,"x":"128.599503","y":"35.87118489","addr":"대구 중구 문화동 12-1","region":"중구","fid":1},{"num":295,"x":"128.5978623","y":"35.86279444","addr":"대구 중구 봉산동 268-5","region":"중구","fid":1},{"num":296,"x":"128.5920018","y":"35.8632534","addr":"대구 중구 남산동 572-2","region":"중구","fid":1},{"num":297,"x":"128.5948229","y":"35.86027194","addr":"대구 중구 남산동 707-1","region":"중구","fid":1},{"num":298,"x":"128.5969527","y":"35.86931911","addr":"대구 중구 남일동 92","region":"중구","fid":1},{"num":299,"x":"128.593259","y":"35.87065756","addr":"대구 중구 상서동 51-1","region":"중구","fid":1},{"num":300,"x":"128.5964026","y":"35.85812336","addr":"대구 중구 남산동 714-2","region":"중구","fid":1},{"num":301,"x":"128.5991865","y":"35.86220401","addr":"대구 중구 봉산동 110","region":"중구","fid":1},{"num":302,"x":"128.608257","y":"35.87272694","addr":"대구 중구 동인동1가 377","region":"중구","fid":1},{"num":303,"x":"128.5943548","y":"35.86999276","addr":"대구 중구 종로1가 41-75","region":"중구","fid":1},{"num":304,"x":"128.6126076","y":"35.87130239","addr":"대구 중구 동인동3가 412","region":"중구","fid":1},{"num":305,"x":"128.6011481","y":"35.85825713","addr":"대구 중구 대봉동 728-38","region":"중구","fid":1},{"num":306,"x":"128.6035378","y":"35.8695649","addr":"대구 중구 동인동2가 50-5","region":"중구","fid":1},{"num":307,"x":"128.6069346","y":"35.87311149","addr":"대구 중구 동인동1가 192-6","region":"중구","fid":1},{"num":308,"x":"128.5897335","y":"35.8605214","addr":"대구 중구 남산동 225-1","region":"중구","fid":1},{"num":309,"x":"128.6016641","y":"35.86118729","addr":"대구 중구 봉산동 168-75","region":"중구","fid":1},{"num":310,"x":"128.6104055","y":"35.87350305","addr":"대구 중구 동인동3가 271-91","region":"중구","fid":1},{"num":311,"x":"128.5838365","y":"35.85916643","addr":"대구 중구 남산동 2466-1","region":"중구","fid":1},{"num":312,"x":"128.6085856","y":"35.85522302","addr":"대구 중구 대봉동 214","region":"중구","fid":1},{"num":313,"x":"128.6131845","y":"35.8730957","addr":"대구 중구 동인동3가 412","region":"중구","fid":1},{"num":314,"x":"128.6054392","y":"35.86369353","addr":"대구 중구 삼덕동2가 270-1","region":"중구","fid":1},{"num":315,"x":"128.5934878","y":"35.87173061","addr":"대구 중구 포정동 87","region":"중구","fid":1},{"num":316,"x":"128.5956177","y":"35.86926058","addr":"대구 중구 남일동 126-2","region":"중구","fid":1},{"num":317,"x":"128.5807666","y":"35.87334656","addr":"대구 중구 달성동 294-1","region":"중구","fid":1},{"num":318,"x":"128.5821552","y":"35.87382508","addr":"대구 중구 달성동 294-1","region":"중구","fid":1},{"num":319,"x":"128.6091763","y":"35.86848656","addr":"대구 중구 동인동4가 179","region":"중구","fid":1},{"num":320,"x":"128.603034","y":"35.86340224","addr":"대구 중구 대봉동 716-6","region":"중구","fid":1},{"num":321,"x":"128.5872072","y":"35.85787001","addr":"대구 중구 남산동 2380-16","region":"중구","fid":1},{"num":322,"x":"128.6741049","y":"35.91735845","addr":"대구 동구 도동 978-104","region":"동구","fid":2},{"num":323,"x":"128.591574","y":"35.86708082","addr":"대구 중구 계산동2가 133","region":"중구","fid":1},{"num":324,"x":"128.6012018","y":"35.86584961","addr":"대구 중구 삼덕동1가 53-10","region":"중구","fid":1},{"num":325,"x":"128.6039109","y":"35.87330317","addr":"대구 중구 동인동1가 62-2","region":"중구","fid":1},{"num":326,"x":"128.5803678","y":"35.8619726","addr":"대구 중구 남산동 2937-1","region":"중구","fid":1},{"num":327,"x":"128.6017989","y":"35.85585418","addr":"대구 중구 대봉동 162-3","region":"중구","fid":1},{"num":328,"x":"128.5829054","y":"35.87309394","addr":"대구 중구 대신동 1-36","region":"중구","fid":1},{"num":329,"x":"128.6020655","y":"35.87479968","addr":"대구 중구 태평로1가 1-99","region":"중구","fid":1},{"num":330,"x":"128.5809714","y":"35.86288226","addr":"대구 중구 남산동 2990","region":"중구","fid":1},{"num":331,"x":"128.6024553","y":"35.86247301","addr":"대구 중구 봉산동 259-1","region":"중구","fid":1},{"num":332,"x":"128.6096076","y":"35.86184017","addr":"대구 중구 대봉동 654-1","region":"중구","fid":1},{"num":333,"x":"128.5886641","y":"35.86644188","addr":"대구 중구 동산동 360","region":"중구","fid":1},{"num":334,"x":"128.6015958","y":"35.87013438","addr":"대구 중구 공평동 12-4","region":"중구","fid":1},{"num":335,"x":"128.5870735","y":"35.8665666","addr":"대구 중구 동산동 837","region":"중구","fid":1},{"num":336,"x":"128.5883901","y":"35.8593244","addr":"대구 중구 남산동 2210-22","region":"중구","fid":1},{"num":337,"x":"128.6046852","y":"35.86133268","addr":"대구 중구 대봉동 55-3","region":"중구","fid":1},{"num":338,"x":"128.6004696","y":"35.86160305","addr":"대구 중구 봉산동 121-1","region":"중구","fid":1},{"num":339,"x":"128.5787979","y":"35.86255812","addr":"대구 중구 남산동 2971-11","region":"중구","fid":1},{"num":340,"x":"128.5830115","y":"35.86694696","addr":"대구 중구 대신동 277-1","region":"중구","fid":1},{"num":341,"x":"128.582802","y":"35.87000138","addr":"대구 중구 대신동 115-96","region":"중구","fid":1},{"num":342,"x":"128.6513497","y":"35.91148499","addr":"대구 동구 도동 99-9","region":"동구","fid":2},{"num":343,"x":"128.6140769","y":"35.87109105","addr":"대구 중구 동인동3가 228","region":"중구","fid":1},{"num":344,"x":"128.588798","y":"35.87235471","addr":"대구 중구 서성로1가 70-15","region":"중구","fid":1},{"num":345,"x":"128.6055922","y":"35.8606055","addr":"대구 중구 대봉동 24-68","region":"중구","fid":1},{"num":346,"x":"128.5887802","y":"35.87411039","addr":"대구 중구 수창동 93-1","region":"중구","fid":1},{"num":347,"x":"128.6892748","y":"35.90608415","addr":"대구 동구 둔산동 364-2","region":"동구","fid":2},{"num":348,"x":"128.5830905","y":"35.86372999","addr":"대구 중구 남산동 2991","region":"중구","fid":1},{"num":349,"x":"128.6015158","y":"35.8634739","addr":"대구 중구 봉산동 165-7","region":"중구","fid":1},{"num":350,"x":"128.6760095","y":"35.8962366","addr":"대구 동구 방촌동 78-6","region":"동구","fid":2},{"num":351,"x":"128.6154073","y":"35.86951889","addr":"대구 중구 동인동3가 412","region":"중구","fid":1},{"num":352,"x":"128.5838457","y":"35.87620957","addr":"대구 중구 달성동 12-23","region":"중구","fid":1},{"num":353,"x":"128.5933684","y":"35.86510969","addr":"대구 중구 남산동 941-27","region":"중구","fid":1},{"num":354,"x":"128.5875072","y":"35.8566489","addr":"대구 중구 남산동 2120-1","region":"중구","fid":1},{"num":355,"x":"128.7496566","y":"35.87318285","addr":"대구 동구 대림동 887","region":"동구","fid":2},{"num":356,"x":"128.5784894","y":"35.8598903","addr":"대구 중구 남산동 2951-1","region":"중구","fid":1},{"num":357,"x":"128.5844749","y":"35.86170192","addr":"대구 중구 남산동 2466-92","region":"중구","fid":1},{"num":358,"x":"128.5905574","y":"35.86606288","addr":"대구 중구 남산동 333-5","region":"중구","fid":1},{"num":359,"x":"128.5903755","y":"35.86175589","addr":"대구 중구 남산동 219","region":"중구","fid":1},{"num":360,"x":"128.577591","y":"35.86048185","addr":"대구 중구 남산동 2951-1","region":"중구","fid":1},{"num":361,"x":"128.5963284","y":"35.87169864","addr":"대구 중구 포정동 58-1","region":"중구","fid":1},{"num":362,"x":"128.5982665","y":"35.85667723","addr":"대구 중구 대봉동 710-4","region":"중구","fid":1},{"num":363,"x":"128.5883767","y":"35.87619361","addr":"대구 중구 수창동 173","region":"중구","fid":1},{"num":364,"x":"128.5801935","y":"35.86680642","addr":"대구 중구 대신동 269-5","region":"중구","fid":1},{"num":365,"x":"128.5983802","y":"35.87146398","addr":"대구 중구 동성로2가 39-10","region":"중구","fid":1},{"num":366,"x":"128.5989526","y":"35.8687166","addr":"대구 중구 공평동 49-4","region":"중구","fid":1},{"num":367,"x":"128.5824081","y":"35.87551042","addr":"대구 중구 달성동 216-1","region":"중구","fid":1},{"num":368,"x":"128.5791122","y":"35.86697503","addr":"대구 중구 대신동 1513","region":"중구","fid":1},{"num":369,"x":"128.5988248","y":"35.86759397","addr":"대구 중구 삼덕동1가 7-1","region":"중구","fid":1},{"num":370,"x":"128.5819309","y":"35.86661899","addr":"대구 중구 대신동 291-69","region":"중구","fid":1},{"num":371,"x":"128.5819337","y":"35.86458887","addr":"대구 중구 대신동 305-1","region":"중구","fid":1},{"num":372,"x":"128.585303","y":"35.87731669","addr":"대구 중구 도원동 7","region":"중구","fid":1},{"num":373,"x":"128.7320748","y":"35.96833324","addr":"대구 동구 능성동 산 116","region":"동구","fid":2},{"num":374,"x":"128.579438","y":"35.87210754","addr":"대구 중구 달성동 294-1","region":"중구","fid":1},{"num":375,"x":"128.5798208","y":"35.86357538","addr":"대구 중구 대신동 2011","region":"중구","fid":1},{"num":376,"x":"128.7243352","y":"35.95807924","addr":"대구 동구 진인동 994","region":"동구","fid":2},{"num":377,"x":"128.5930604","y":"35.86371604","addr":"대구 중구 남산동 623-12","region":"중구","fid":1},{"num":378,"x":"128.5948183","y":"35.86237232","addr":"대구 중구 남산동 654-1","region":"중구","fid":1},{"num":379,"x":"128.5971648","y":"35.85900335","addr":"대구 중구 남산동 731-6","region":"중구","fid":1},{"num":380,"x":"128.5968296","y":"35.86310984","addr":"대구 중구 남산동 676-9","region":"중구","fid":1},{"num":381,"x":"128.5909066","y":"35.86846308","addr":"대구 중구 계산동2가 25","region":"중구","fid":1},{"num":382,"x":"128.5905228","y":"35.87079292","addr":"대구 중구 하서동 28-1","region":"중구","fid":1},{"num":383,"x":"128.5857511","y":"35.86440279","addr":"대구 중구 남산동 156-8","region":"중구","fid":1},{"num":384,"x":"128.5881801","y":"35.86873729","addr":"대구 중구 동산동 186-1","region":"중구","fid":1},{"num":385,"x":"128.6563334","y":"35.88907355","addr":"대구 동구 검사동 908-39","region":"동구","fid":2},{"num":386,"x":"128.5862759","y":"35.87040268","addr":"대구 중구 동산동 94-1","region":"중구","fid":1},{"num":387,"x":"128.5980997","y":"35.85856942","addr":"대구 중구 대봉동 594-3","region":"중구","fid":1},{"num":388,"x":"128.7387304","y":"35.87233806","addr":"대구 동구 괴전동 208-1","region":"동구","fid":2},{"num":389,"x":"128.7505151","y":"35.85961186","addr":"대구 동구 금강동 68","region":"동구","fid":2},{"num":390,"x":"128.6630047","y":"35.88606625","addr":"대구 동구 검사동 748-4","region":"동구","fid":2},{"num":391,"x":"128.6095304","y":"35.86631538","addr":"대구 중구 삼덕동3가 383","region":"중구","fid":1},{"num":392,"x":"128.6532237","y":"35.98601326","addr":"대구 동구 신용동 478","region":"동구","fid":2},{"num":393,"x":"128.60502","y":"35.86737858","addr":"대구 중구 삼덕동2가 29-27","region":"중구","fid":1},{"num":394,"x":"128.6037858","y":"35.86817334","addr":"대구 중구 동인동2가 42","region":"중구","fid":1},{"num":395,"x":"128.6114781","y":"35.86286261","addr":"대구 중구 삼덕동3가 379","region":"중구","fid":1},{"num":396,"x":"128.717722","y":"35.95532715","addr":"대구 동구 진인동 556-1","region":"동구","fid":2},{"num":397,"x":"128.7447994","y":"35.87407446","addr":"대구 동구 대림동 886-2","region":"동구","fid":2},{"num":398,"x":"128.6121809","y":"35.87016986","addr":"대구 중구 동인동3가 192-44","region":"중구","fid":1},{"num":399,"x":"128.6556382","y":"35.97089737","addr":"대구 동구 내동 산 43","region":"동구","fid":2},{"num":400,"x":"128.5825515","y":"35.87176946","addr":"대구 중구 대신동 69-13","region":"중구","fid":1},{"num":401,"x":"128.6021008","y":"35.8714662","addr":"대구 중구 동문동 13-11","region":"중구","fid":1},{"num":402,"x":"128.5872503","y":"35.86273372","addr":"대구 중구 남산동 127-12","region":"중구","fid":1},{"num":403,"x":"128.5827403","y":"35.86146303","addr":"대구 중구 남산동 2466-70","region":"중구","fid":1},{"num":404,"x":"128.6022082","y":"35.86595423","addr":"대구 중구 삼덕동1가 55-40","region":"중구","fid":1},{"num":405,"x":"128.6757491","y":"35.98495887","addr":"대구 동구 신무동 690-6","region":"동구","fid":2},{"num":406,"x":"128.6013529","y":"35.86840338","addr":"대구 중구 공평동 59-8","region":"중구","fid":1},{"num":407,"x":"128.6025529","y":"35.8690026","addr":"대구 중구 동인동2가 38","region":"중구","fid":1},{"num":408,"x":"128.680038","y":"35.97410886","addr":"대구 동구 용수동 596-2","region":"동구","fid":2},{"num":409,"x":"128.590486","y":"35.85691476","addr":"대구 중구 남산동 2321","region":"중구","fid":1},{"num":410,"x":"128.6395486","y":"35.9835961","addr":"대구 동구 중대동 725-2","region":"동구","fid":2},{"num":411,"x":"128.5845678","y":"35.87274976","addr":"대구 중구 시장북로 157","region":"중구","fid":1},{"num":412,"x":"128.5912999","y":"35.87142768","addr":"대구 중구 서문로1가 24","region":"중구","fid":1},{"num":413,"x":"128.7087197","y":"35.97013643","addr":"대구 동구 도학동 440","region":"동구","fid":2},{"num":414,"x":"128.6006342","y":"35.85611783","addr":"대구 중구 대봉동 707-5","region":"중구","fid":1},{"num":415,"x":"128.6305997","y":"35.97909204","addr":"대구 동구 덕곡동 719-2","region":"동구","fid":2},{"num":416,"x":"128.5976222","y":"35.860688","addr":"대구 중구 남산동 687-19","region":"중구","fid":1},{"num":417,"x":"128.5851264","y":"35.86268217","addr":"대구 중구 남산동 108-8","region":"중구","fid":1},{"num":418,"x":"128.5895681","y":"35.85736492","addr":"대구 중구 남산동 2116-56","region":"중구","fid":1},{"num":419,"x":"128.6338712","y":"35.98154009","addr":"대구 동구 중대동 1122","region":"동구","fid":2},{"num":420,"x":"128.5869356","y":"35.87279328","addr":"대구 중구 인교동 278-26","region":"중구","fid":1},{"num":421,"x":"128.5900594","y":"35.87388621","addr":"대구 중구 수창동 99-1","region":"중구","fid":1},{"num":422,"x":"128.5896697","y":"35.86541861","addr":"대구 중구 남산동 267-1","region":"중구","fid":1},{"num":423,"x":"128.7539334","y":"35.87382439","addr":"대구 동구 사복동 851","region":"동구","fid":2},{"num":424,"x":"128.7073054","y":"35.94839537","addr":"대구 동구 백안동 산 110-1","region":"동구","fid":2},{"num":425,"x":"128.597737","y":"35.87049315","addr":"대구 중구 동성로2가 88-22","region":"중구","fid":1},{"num":426,"x":"128.7133146","y":"35.95777412","addr":"대구 동구 진인동 587","region":"동구","fid":2},{"num":427,"x":"128.7153946","y":"35.95880303","addr":"대구 동구 진인동 319","region":"동구","fid":2},{"num":428,"x":"128.7400949","y":"35.9630945","addr":"대구 동구 능성동 316","region":"동구","fid":2},{"num":429,"x":"128.5862775","y":"35.87811261","addr":"대구 중구 태평로3가 176-1","region":"중구","fid":1},{"num":430,"x":"128.5814514","y":"35.87484046","addr":"대구 중구 달성동 294-1","region":"중구","fid":1},{"num":431,"x":"128.5944299","y":"35.86544167","addr":"대구 중구 남산동 936-1","region":"중구","fid":1},{"num":432,"x":"128.7333601","y":"35.96442448","addr":"대구 동구 능성동 590","region":"동구","fid":2},{"num":433,"x":"128.5924331","y":"35.86645938","addr":"대구 중구 계산동2가 200","region":"중구","fid":1},{"num":434,"x":"128.5921533","y":"35.86961794","addr":"대구 중구 수동 35-3","region":"중구","fid":1},{"num":435,"x":"128.758136","y":"35.87771607","addr":"대구 동구 숙천동 181","region":"동구","fid":2},{"num":436,"x":"128.5827173","y":"35.85957115","addr":"대구 중구 남산동 2482-1","region":"중구","fid":1},{"num":437,"x":"128.5977312","y":"35.86381817","addr":"대구 중구 봉산동 57","region":"중구","fid":1},{"num":439,"x":"128.742416","y":"35.88260742"},{"num":439,"x":"128.5871702","y":"35.86054528","addr":"대구 중구 남산동 2434","region":"중구","fid":1},{"num":440,"x":"128.5853904","y":"35.86795687","addr":"대구 중구 동산동 194","region":"중구","fid":1},{"num":441,"x":"128.5847582","y":"35.8582173","addr":"대구 중구 남산동 3012","region":"중구","fid":1},{"num":442,"x":"128.5816585","y":"35.87274746","addr":"대구 중구 달성동 294-1","region":"중구","fid":1},{"num":443,"x":"128.7618438","y":"35.88751532","addr":"대구 동구 내곡동 133","region":"동구","fid":2},{"num":444,"x":"128.6033768","y":"35.85762951","addr":"대구 중구 대봉동 760","region":"중구","fid":1},{"num":445,"x":"128.606838","y":"35.86565592","addr":"대구 중구 삼덕동2가 50","region":"중구","fid":1},{"num":446,"x":"128.6524341","y":"35.87145086","addr":"대구 수성구 만촌동 1244-1","region":"수성구","fid":6},{"num":447,"x":"128.5932553","y":"35.87670385","addr":"대구 중구 태평로2가 38-1","region":"중구","fid":1},{"num":448,"x":"128.5895579","y":"35.87149123","addr":"대구 중구 서문로2가 12-2","region":"중구","fid":1},{"num":449,"x":"128.6026569","y":"35.86059549","addr":"대구 중구 봉산동 203-1","region":"중구","fid":1},{"num":450,"x":"128.7383319","y":"35.86388041","addr":"대구 동구 금강동 1015","region":"동구","fid":2},{"num":451,"x":"128.5886323","y":"35.86388517","addr":"대구 중구 남산동 130-2","region":"중구","fid":1},{"num":452,"x":"128.7371576","y":"35.87564992","addr":"대구 동구 신서동 1179","region":"동구","fid":2},{"num":453,"x":"128.7365523","y":"35.88526719","addr":"대구 동구 신서동 1180","region":"동구","fid":2},{"num":454,"x":"128.7092963","y":"35.88166317","addr":"대구 동구 율암동 1103-5","region":"동구","fid":2},{"num":455,"x":"128.7524711","y":"35.87546363","addr":"대구 동구 사복동 846","region":"동구","fid":2},{"num":456,"x":"128.6875867","y":"35.87982665","addr":"대구 동구 용계동 362-1","region":"동구","fid":2},{"num":457,"x":"128.6034844","y":"35.87453071","addr":"대구 중구 태평로1가 23-1","region":"중구","fid":1},{"num":458,"x":"128.6091157","y":"35.87006007","addr":"대구 중구 동인동3가 146","region":"중구","fid":1},{"num":459,"x":"128.607306","y":"35.86981809","addr":"대구 중구 동인동2가 108-9","region":"중구","fid":1},{"num":460,"x":"128.6882732","y":"35.88145271","addr":"대구 동구 신평동 272","region":"동구","fid":2},{"num":461,"x":"128.6219773","y":"35.98871765","addr":"대구 동구 송정동 810-1","region":"동구","fid":2},{"num":462,"x":"128.681232","y":"35.8868376","addr":"대구 동구 신평동 436","region":"동구","fid":2},{"num":463,"x":"128.7197658","y":"35.88266145","addr":"대구 동구 각산동 1063","region":"동구","fid":2},{"num":464,"x":"128.7120043","y":"35.87868542","addr":"대구 동구 율암동 1151-3","region":"동구","fid":2},{"num":465,"x":"128.5833386","y":"35.86833055","addr":"대구 중구 대신동 115-14","region":"중구","fid":1},{"num":466,"x":"128.5827454","y":"35.86557933","addr":"대구 중구 대신동 305-1","region":"중구","fid":1},{"num":467,"x":"128.7392091","y":"35.8763389","addr":"대구 동구 동내동 1119-3","region":"동구","fid":2},{"num":468,"x":"128.7260987","y":"35.88705781","addr":"대구 동구 각산동 1046","region":"동구","fid":2},{"num":469,"x":"128.7252555","y":"35.88651078","addr":"대구 동구 각산동 1046","region":"동구","fid":2},{"num":470,"x":"128.685447","y":"35.87575499","addr":"대구 동구 용계동 887-24","region":"동구","fid":2},{"num":471,"x":"128.6818719","y":"35.8754004","addr":"대구 동구 용계동 518-5","region":"동구","fid":2},{"num":472,"x":"128.7217212","y":"35.87091755","addr":"대구 동구 각산동 292-8","region":"동구","fid":2},{"num":473,"x":"128.7116187","y":"35.86948662","addr":"대구 동구 서호동 86-1","region":"동구","fid":2},{"num":474,"x":"128.5896519","y":"35.86826807","addr":"대구 중구 계산동1가 70","region":"중구","fid":1},{"num":475,"x":"128.6359528","y":"35.92644518","addr":"대구 동구 봉무동 1624","region":"동구","fid":2},{"num":476,"x":"128.6379657","y":"35.97936885","addr":"대구 동구 중대동 560-2","region":"동구","fid":2},{"num":477,"x":"128.7465042","y":"35.87354137","addr":"대구 동구 대림동 886-3","region":"동구","fid":2},{"num":478,"x":"128.6712856","y":"35.96187032","addr":"대구 동구 미대동 145","region":"동구","fid":2},{"num":479,"x":"128.6836788","y":"35.87551287","addr":"대구 동구 용계동 1018-1","region":"동구","fid":2},{"num":480,"x":"128.7511452","y":"35.87424465","addr":"대구 동구 대림동 888-2","region":"동구","fid":2},{"num":481,"x":"128.5847993","y":"35.85984123","addr":"대구 중구 남산동 2466-27","region":"중구","fid":1},{"num":482,"x":"128.6846881","y":"35.86436056","addr":"대구 동구 율하동 813-35","region":"동구","fid":2},{"num":483,"x":"128.7370052","y":"35.88107722","addr":"대구 동구 동내동 1145","region":"동구","fid":2},{"num":484,"x":"128.7113811","y":"35.8920244","addr":"대구 동구 상매동 510","region":"동구","fid":2},{"num":485,"x":"128.7311749","y":"35.88086297","addr":"대구 동구 신서동 1143","region":"동구","fid":2},{"num":486,"x":"128.6311693","y":"35.88661764","addr":"대구 동구 신암동 1318-5","region":"동구","fid":2},{"num":487,"x":"128.6020007","y":"35.86694269","addr":"대구 중구 삼덕동1가 59-6","region":"중구","fid":1},{"num":488,"x":"128.6983799","y":"35.86535072","addr":"대구 동구 율하동 1461","region":"동구","fid":2},{"num":489,"x":"128.6376548","y":"35.9060238","addr":"대구 동구 불로동 701","region":"동구","fid":2},{"num":490,"x":"128.646765","y":"35.91081221","addr":"대구 동구 불로동 523-4","region":"동구","fid":2},{"num":491,"x":"128.652723","y":"35.91099642","addr":"대구 동구 도동 1054-41","region":"동구","fid":2},{"num":492,"x":"128.6011854","y":"35.87252665","addr":"대구 중구 완전동 5-39","region":"중구","fid":1},{"num":493,"x":"128.6521483","y":"35.88310745","addr":"대구 동구 효목동 1314","region":"동구","fid":2},{"num":494,"x":"128.6385572","y":"35.92719984","addr":"대구 동구 봉무동 1624","region":"동구","fid":2},{"num":495,"x":"128.5841642","y":"35.85727377","addr":"대구 중구 남산동 2267-1","region":"중구","fid":1},{"num":496,"x":"128.6307707","y":"35.88912456","addr":"대구 동구 신암동 1760","region":"동구","fid":2},{"num":497,"x":"128.6366271","y":"35.88437718","addr":"대구 동구 신암동 369","region":"동구","fid":2},{"num":498,"x":"128.643916","y":"35.88738864","addr":"대구 동구 효목동 3-11","region":"동구","fid":2},{"num":499,"x":"128.6357348","y":"35.88923893","addr":"대구 동구 신암동 71-11","region":"동구","fid":2},{"num":500,"x":"128.6455059","y":"35.88351959","addr":"대구 동구 효목동 134-1","region":"동구","fid":2},{"num":501,"x":"128.6470773","y":"35.8808914","addr":"대구 동구 효목동 176-11","region":"동구","fid":2},{"num":502,"x":"128.6441889","y":"35.88276346","addr":"대구 동구 효목동 126-79","region":"동구","fid":2},{"num":503,"x":"128.6488573","y":"35.88137869","addr":"대구 동구 효목동 173-1","region":"동구","fid":2},{"num":504,"x":"128.634794","y":"35.88156422","addr":"대구 동구 신암동 369","region":"동구","fid":2},{"num":505,"x":"128.6466327","y":"35.87953125","addr":"대구 동구 효목동 160-15","region":"동구","fid":2},{"num":506,"x":"128.6451061","y":"35.8777747","addr":"대구 동구 효목동 647-11","region":"동구","fid":2},{"num":507,"x":"128.693597","y":"35.93281722","addr":"대구 동구 평광동 1078","region":"동구","fid":2},{"num":508,"x":"128.6398251","y":"35.88241634","addr":"대구 동구 효목동 46-18","region":"동구","fid":2},{"num":509,"x":"128.6414752","y":"35.87652401","addr":"대구 동구 효목동 459-8","region":"동구","fid":2},{"num":510,"x":"128.6482589","y":"35.87718007","addr":"대구 동구 효목동 209","region":"동구","fid":2},{"num":511,"x":"128.6498706","y":"35.87983995","addr":"대구 동구 효목동 183-3","region":"동구","fid":2},{"num":512,"x":"128.647749","y":"35.87884097","addr":"대구 동구 효목동 191-15","region":"동구","fid":2},{"num":513,"x":"128.6341562","y":"35.8759363","addr":"대구 동구 신천동 424-8","region":"동구","fid":2},{"num":514,"x":"128.624197","y":"35.87614736","addr":"대구 동구 신천동 44-29","region":"동구","fid":2},{"num":515,"x":"128.6186679","y":"35.88425399","addr":"대구 동구 신암동 722-291","region":"동구","fid":2},{"num":516,"x":"128.6399102","y":"35.87982926","addr":"대구 동구 효목동 377-20","region":"동구","fid":2},{"num":517,"x":"128.6187342","y":"35.8794886","addr":"대구 동구 신암동 367","region":"동구","fid":2},{"num":518,"x":"128.6380984","y":"35.87674261","addr":"대구 동구 효목동 418-3","region":"동구","fid":2},{"num":519,"x":"128.6212779","y":"35.88503508","addr":"대구 동구 신암동 716-87","region":"동구","fid":2},{"num":520,"x":"128.6217856","y":"35.88055013","addr":"대구 동구 신암동 367","region":"동구","fid":2},{"num":521,"x":"128.6231775","y":"35.88439785","addr":"대구 동구 신암동 1341-11","region":"동구","fid":2},{"num":522,"x":"128.6204206","y":"35.88695744","addr":"대구 동구 신암동 694-10","region":"동구","fid":2},{"num":523,"x":"128.6202362","y":"35.88516143","addr":"대구 동구 신암동 1846","region":"동구","fid":2},{"num":524,"x":"128.6116781","y":"35.87781344","addr":"대구 동구 신암동 1289-2","region":"동구","fid":2},{"num":525,"x":"128.6306512","y":"35.88395195","addr":"대구 동구 신암동 251-1","region":"동구","fid":2},{"num":526,"x":"128.6165385","y":"35.87779605","addr":"대구 동구 신암동 458-30","region":"동구","fid":2},{"num":527,"x":"128.6181707","y":"35.8810667","addr":"대구 동구 신암동 164-15","region":"동구","fid":2},{"num":528,"x":"128.6114059","y":"35.87667696","addr":"대구 동구 신암동 1299-6","region":"동구","fid":2},{"num":529,"x":"128.6934331","y":"35.93494397","addr":"대구 동구 평광동 1543-1","region":"동구","fid":2},{"num":530,"x":"128.6586792","y":"35.87889863","addr":"대구 동구 효목동 1012","region":"동구","fid":2},{"num":531,"x":"128.6364221","y":"35.87316874","addr":"대구 동구 신천동 482-4","region":"동구","fid":2},{"num":532,"x":"128.6320712","y":"35.87055617","addr":"대구 동구 신천동 344-33","region":"동구","fid":2},{"num":533,"x":"128.6392047","y":"35.87328857","addr":"대구 동구 효목동 647","region":"동구","fid":2},{"num":534,"x":"128.6342978","y":"35.87083934","addr":"대구 동구 신천동 357-23","region":"동구","fid":2},{"num":535,"x":"128.6924058","y":"35.93502919","addr":"대구 동구 평광동 1543-1","region":"동구","fid":2},{"num":536,"x":"128.6227281","y":"35.885501","addr":"대구 동구 신암동 608-6","region":"동구","fid":2},{"num":537,"x":"128.6234936","y":"35.88331331","addr":"대구 동구 신암동 603-351","region":"동구","fid":2},{"num":538,"x":"128.6358403","y":"35.88816537","addr":"대구 동구 신암동 94-14","region":"동구","fid":2},{"num":539,"x":"128.6370519","y":"35.87742849","addr":"대구 동구 효목동 647","region":"동구","fid":2},{"num":540,"x":"128.638013","y":"35.87547097","addr":"대구 동구 효목동 647-15","region":"동구","fid":2},{"num":541,"x":"128.6325019","y":"35.88755926","addr":"대구 동구 신암동 132-1","region":"동구","fid":2},{"num":542,"x":"128.6429003","y":"35.8851825","addr":"대구 동구 효목동 209","region":"동구","fid":2},{"num":543,"x":"128.6432311","y":"35.88618126","addr":"대구 동구 효목동 85-7","region":"동구","fid":2},{"num":544,"x":"128.6345696","y":"35.88815156","addr":"대구 동구 신암동 129-85","region":"동구","fid":2},{"num":545,"x":"128.6391114","y":"35.87816203","addr":"대구 동구 효목동 383-14","region":"동구","fid":2},{"num":546,"x":"128.6371032","y":"35.88604516","addr":"대구 동구 신암동 98-1","region":"동구","fid":2},{"num":547,"x":"128.6452083","y":"35.87898884","addr":"대구 동구 효목동 597-3","region":"동구","fid":2},{"num":548,"x":"128.6377044","y":"35.87944228","addr":"대구 동구 효목동 647","region":"동구","fid":2},{"num":549,"x":"128.6391554","y":"35.87712265","addr":"대구 동구 효목동 424-15","region":"동구","fid":2},{"num":550,"x":"128.6440421","y":"35.87942691","addr":"대구 동구 효목동 647","region":"동구","fid":2},{"num":551,"x":"128.6359711","y":"35.87693646","addr":"대구 동구 효목동 394-8","region":"동구","fid":2},{"num":552,"x":"128.6289605","y":"35.88964982","addr":"대구 동구 신암동 1620-4","region":"동구","fid":2},{"num":553,"x":"128.6327056","y":"35.87549824","addr":"대구 동구 신천동 441-2","region":"동구","fid":2},{"num":554,"x":"128.633507","y":"35.88348738","addr":"대구 동구 신암동 331-25","region":"동구","fid":2},{"num":555,"x":"128.6335511","y":"35.87694327","addr":"대구 동구 신천동 393-6","region":"동구","fid":2},{"num":556,"x":"128.6293739","y":"35.88193291","addr":"대구 동구 신암동 369","region":"동구","fid":2},{"num":557,"x":"128.6434679","y":"35.88361782","addr":"대구 동구 효목동 126-26","region":"동구","fid":2},{"num":558,"x":"128.6445164","y":"35.87589985","addr":"대구 동구 효목동 633","region":"동구","fid":2},{"num":559,"x":"128.6388235","y":"35.88454118","addr":"대구 동구 효목동 44-1","region":"동구","fid":2},{"num":560,"x":"128.6268277","y":"35.87924667","addr":"대구 동구 신암동 207-77","region":"동구","fid":2},{"num":561,"x":"128.6455769","y":"35.88186583","addr":"대구 동구 효목동 209","region":"동구","fid":2},{"num":562,"x":"128.6283092","y":"35.89046625","addr":"대구 동구 신암동 1620-4","region":"동구","fid":2},{"num":563,"x":"128.6280561","y":"35.88747455","addr":"대구 동구 신암동 1812","region":"동구","fid":2},{"num":564,"x":"128.6421276","y":"35.88382035","addr":"대구 동구 효목동 54-23","region":"동구","fid":2},{"num":565,"x":"128.6410923","y":"35.88625823","addr":"대구 동구 효목동 67-9","region":"동구","fid":2},{"num":566,"x":"128.6428182","y":"35.88276386","addr":"대구 동구 효목동 126-37","region":"동구","fid":2},{"num":567,"x":"128.6376072","y":"35.88933643","addr":"대구 동구 신암동 54-47","region":"동구","fid":2},{"num":568,"x":"128.6463887","y":"35.88440127","addr":"대구 동구 효목동 32-1","region":"동구","fid":2},{"num":569,"x":"128.6456713","y":"35.88543078","addr":"대구 동구 효목동 9","region":"동구","fid":2},{"num":570,"x":"128.638399","y":"35.8856208","addr":"대구 동구 효목동 962-7","region":"동구","fid":2},{"num":571,"x":"128.6364885","y":"35.88203756","addr":"대구 동구 신암동 302-3","region":"동구","fid":2},{"num":572,"x":"128.6345995","y":"35.88532382","addr":"대구 동구 신암동 341-1","region":"동구","fid":2},{"num":573,"x":"128.6373806","y":"35.88809516","addr":"대구 동구 신암동 28","region":"동구","fid":2},{"num":574,"x":"128.6384493","y":"35.88813241","addr":"대구 동구 신암동 26-29","region":"동구","fid":2},{"num":575,"x":"128.6300893","y":"35.88780989","addr":"대구 동구 신암동 136-260","region":"동구","fid":2},{"num":576,"x":"128.642169","y":"35.87544337","addr":"대구 동구 효목동 547","region":"동구","fid":2},{"num":577,"x":"128.6299255","y":"35.88654488","addr":"대구 동구 신암동 136-226","region":"동구","fid":2},{"num":578,"x":"128.6264671","y":"35.86941884","addr":"대구 동구 신천동 124-3","region":"동구","fid":2},{"num":579,"x":"128.6263169","y":"35.87131656","addr":"대구 동구 신천동 741","region":"동구","fid":2},{"num":580,"x":"128.6389761","y":"35.87590631","addr":"대구 동구 효목동 432-9","region":"동구","fid":2},{"num":581,"x":"128.6268015","y":"35.88084846","addr":"대구 동구 신암동 235-1","region":"동구","fid":2},{"num":582,"x":"128.636771","y":"35.8720753","addr":"대구 동구 신천동 481-1","region":"동구","fid":2},{"num":583,"x":"128.6408649","y":"35.87497","addr":"대구 동구 효목동 436-1","region":"동구","fid":2},{"num":584,"x":"128.6488839","y":"35.87846699","addr":"대구 동구 효목동 186-7","region":"동구","fid":2},{"num":585,"x":"128.6284593","y":"35.88304295","addr":"대구 동구 신암동 253-14","region":"동구","fid":2},{"num":586,"x":"128.6325959","y":"35.88538942","addr":"대구 동구 신암동 288-4","region":"동구","fid":2},{"num":587,"x":"128.6374462","y":"35.8783599","addr":"대구 동구 효목동 386-2","region":"동구","fid":2},{"num":588,"x":"128.6401769","y":"35.8882581","addr":"대구 동구 신암동 1503","region":"동구","fid":2},{"num":589,"x":"128.6452032","y":"35.88638176","addr":"대구 동구 효목동 9","region":"동구","fid":2},{"num":590,"x":"128.635053","y":"35.87861072","addr":"대구 동구 효목동 280-10","region":"동구","fid":2},{"num":591,"x":"128.6347012","y":"35.89001423","addr":"대구 동구 신암동 80","region":"동구","fid":2},{"num":592,"x":"128.6299705","y":"35.88109112","addr":"대구 동구 신암동 259-5","region":"동구","fid":2},{"num":593,"x":"128.7167858","y":"35.86971064","addr":"대구 동구 동호동 105-4","region":"동구","fid":2},{"num":594,"x":"128.6184599","y":"35.87660865","addr":"대구 동구 신암동 493-12","region":"동구","fid":2},{"num":595,"x":"128.6514455","y":"35.88050511","addr":"대구 동구 효목동 1054","region":"동구","fid":2},{"num":596,"x":"128.626927","y":"35.87722103","addr":"대구 동구 신천동 70-1","region":"동구","fid":2},{"num":597,"x":"128.6210676","y":"35.887965","addr":"대구 동구 신암동 657-53","region":"동구","fid":2},{"num":598,"x":"128.6283015","y":"35.88861097","addr":"대구 동구 신암동 680-71","region":"동구","fid":2},{"num":599,"x":"128.6369577","y":"35.89075349","addr":"대구 동구 신암동 67","region":"동구","fid":2},{"num":600,"x":"128.6355652","y":"35.87529976","addr":"대구 동구 신천동 409-4","region":"동구","fid":2},{"num":601,"x":"128.6374319","y":"35.88369966","addr":"대구 동구 신암동 369","region":"동구","fid":2},{"num":602,"x":"128.7095993","y":"35.86185549","addr":"대구 동구 서호동 283","region":"동구","fid":2},{"num":603,"x":"128.6458038","y":"35.88057127","addr":"대구 동구 효목동 161-3","region":"동구","fid":2},{"num":604,"x":"128.632652","y":"35.88965155","addr":"대구 동구 신암동 134-30","region":"동구","fid":2},{"num":605,"x":"128.6311907","y":"35.8850481","addr":"대구 동구 신암동 250-11","region":"동구","fid":2},{"num":606,"x":"128.6300799","y":"35.8826685","addr":"대구 동구 신암동 257-23","region":"동구","fid":2},{"num":607,"x":"128.6288745","y":"35.87294509","addr":"대구 동구 신천동 292-11","region":"동구","fid":2},{"num":608,"x":"128.6300279","y":"35.87204066","addr":"대구 동구 신천동 322-9","region":"동구","fid":2},{"num":609,"x":"128.6280049","y":"35.86907666","addr":"대구 동구 신천동 113-4","region":"동구","fid":2},{"num":610,"x":"128.6184334","y":"35.86941702","addr":"대구 동구 신천동 808-20","region":"동구","fid":2},{"num":611,"x":"128.6195481","y":"35.86853592","addr":"대구 동구 신천동 832-8","region":"동구","fid":2},{"num":612,"x":"128.6258487","y":"35.87269192","addr":"대구 동구 신천동 193-6","region":"동구","fid":2},{"num":613,"x":"128.6224324","y":"35.87301702","addr":"대구 동구 신천동 264-14","region":"동구","fid":2},{"num":614,"x":"128.6229221","y":"35.87465019","addr":"대구 동구 신천동 278-12","region":"동구","fid":2},{"num":615,"x":"128.6236811","y":"35.86986774","addr":"대구 동구 신천동 171-10","region":"동구","fid":2},{"num":616,"x":"128.6196802","y":"35.87403244","addr":"대구 동구 신천동 513","region":"동구","fid":2},{"num":617,"x":"128.6242321","y":"35.87263545","addr":"대구 동구 신천동 261-8","region":"동구","fid":2},{"num":618,"x":"128.6203453","y":"35.87227574","addr":"대구 동구 신천동 689-1","region":"동구","fid":2},{"num":619,"x":"128.6219958","y":"35.87408222","addr":"대구 동구 신천동 276-2","region":"동구","fid":2},{"num":620,"x":"128.6233825","y":"35.87349759","addr":"대구 동구 신천동 261-3","region":"동구","fid":2},{"num":621,"x":"128.6207122","y":"35.86952306","addr":"대구 동구 신천동 786-33","region":"동구","fid":2},{"num":622,"x":"128.6344679","y":"35.87474025","addr":"대구 동구 신천동 743","region":"동구","fid":2},{"num":623,"x":"128.6310781","y":"35.8711945","addr":"대구 동구 신천동 341-5","region":"동구","fid":2},{"num":624,"x":"128.6171418","y":"35.87055941","addr":"대구 동구 신천동 645-1","region":"동구","fid":2},{"num":625,"x":"128.6274163","y":"35.86784941","addr":"대구 동구 신천동 148-4","region":"동구","fid":2},{"num":626,"x":"128.6240198","y":"35.87441278","addr":"대구 동구 신천동 279-16","region":"동구","fid":2},{"num":627,"x":"128.6381926","y":"35.87337396","addr":"대구 동구 효목동 507-11","region":"동구","fid":2},{"num":628,"x":"128.640726","y":"35.87330269","addr":"대구 동구 효목동 526-2","region":"동구","fid":2},{"num":629,"x":"128.6346281","y":"35.86966985","addr":"대구 동구 신천동 743","region":"동구","fid":2},{"num":630,"x":"128.633518","y":"35.8868279","addr":"대구 동구 신암동 123-16","region":"동구","fid":2},{"num":631,"x":"128.6335503","y":"35.88909718","addr":"대구 동구 신암동 134-159","region":"동구","fid":2},{"num":632,"x":"128.6330714","y":"35.88140781","addr":"대구 동구 신암동 350-5","region":"동구","fid":2},{"num":633,"x":"128.6328809","y":"35.88429142","addr":"대구 동구 신암동 326-5","region":"동구","fid":2},{"num":634,"x":"128.7029202","y":"35.93235246","addr":"대구 동구 평광동 558","region":"동구","fid":2},{"num":635,"x":"128.6271719","y":"35.87470597","addr":"대구 동구 신천동 89-1","region":"동구","fid":2},{"num":636,"x":"128.6277385","y":"35.87284594","addr":"대구 동구 신천동 742","region":"동구","fid":2},{"num":637,"x":"128.6256246","y":"35.87458872","addr":"대구 동구 신천동 741","region":"동구","fid":2},{"num":638,"x":"128.6257228","y":"35.86791276","addr":"대구 동구 신천동 741","region":"동구","fid":2},{"num":639,"x":"128.6214854","y":"35.87018968","addr":"대구 동구 신천동 671-22","region":"동구","fid":2},{"num":640,"x":"128.6211529","y":"35.87139503","addr":"대구 동구 신천동 682-26","region":"동구","fid":2},{"num":641,"x":"128.6325013","y":"35.87165099","addr":"대구 동구 신천동 478","region":"동구","fid":2},{"num":642,"x":"128.6225367","y":"35.87034482","addr":"대구 동구 신천동 741","region":"동구","fid":2},{"num":643,"x":"128.6157584","y":"35.87363968","addr":"대구 동구 신천동 630","region":"동구","fid":2},{"num":644,"x":"128.6172177","y":"35.8738379","addr":"대구 동구 신천동 604-18","region":"동구","fid":2},{"num":645,"x":"128.6179557","y":"35.87454925","addr":"대구 동구 신천동 537-12","region":"동구","fid":2},{"num":646,"x":"128.62074139999999","y":"35.87327447","addr":"대구 동구 신천동 741","region":"동구","fid":2},{"num":647,"x":"128.6239398","y":"35.89022037","addr":"대구 동구 신암동 664-19","region":"동구","fid":2},{"num":648,"x":"128.6240866","y":"35.88635266","addr":"대구 동구 신암동 628-3","region":"동구","fid":2},{"num":649,"x":"128.6231628","y":"35.88059459","addr":"대구 동구 신암동 367","region":"동구","fid":2},{"num":650,"x":"128.6246344","y":"35.88844823","addr":"대구 동구 신암동 647","region":"동구","fid":2},{"num":651,"x":"128.6193686","y":"35.8702057","addr":"대구 동구 신천동 656-25","region":"동구","fid":2},{"num":652,"x":"128.7509483","y":"35.87326088","addr":"대구 동구 대림동 898","region":"동구","fid":2},{"num":653,"x":"128.6173251","y":"35.872043","addr":"대구 동구 신천동 633","region":"동구","fid":2},{"num":654,"x":"128.6381811","y":"35.93082567","addr":"대구 동구 봉무동 산 19","region":"동구","fid":2},{"num":655,"x":"128.6369038","y":"35.93132606","addr":"대구 동구 봉무동 1019","region":"동구","fid":2},{"num":656,"x":"128.6375212","y":"35.92964532","addr":"대구 동구 봉무동 1051-4","region":"동구","fid":2},{"num":657,"x":"128.6226613","y":"35.87197574","addr":"대구 동구 신천동 185-1","region":"동구","fid":2},{"num":658,"x":"128.6210763","y":"35.87451109","addr":"대구 동구 신천동 274-3","region":"동구","fid":2},{"num":659,"x":"128.6323249","y":"35.87687536","addr":"대구 동구 신천동 386-5","region":"동구","fid":2},{"num":660,"x":"128.6444112","y":"35.93014902","addr":"대구 동구 봉무동 1358-12","region":"동구","fid":2},{"num":661,"x":"128.6323238","y":"35.88302245","addr":"대구 동구 신암동 329-28","region":"동구","fid":2},{"num":662,"x":"128.6211382","y":"35.8681585","addr":"대구 동구 신천동 787-4","region":"동구","fid":2},{"num":663,"x":"128.6367164","y":"35.92560328","addr":"대구 동구 봉무동 1624","region":"동구","fid":2},{"num":664,"x":"128.6384766","y":"35.9291986","addr":"대구 동구 봉무동 산 23","region":"동구","fid":2},{"num":665,"x":"128.6447155","y":"35.928483","addr":"대구 동구 봉무동 245","region":"동구","fid":2},{"num":666,"x":"128.6438332","y":"35.92604667","addr":"대구 동구 봉무동 1581","region":"동구","fid":2},{"num":667,"x":"128.6461525","y":"35.90932766","addr":"대구 동구 도동 978-69","region":"동구","fid":2},{"num":668,"x":"128.6358855","y":"35.90126588","addr":"대구 동구 불로동 807","region":"동구","fid":2},{"num":669,"x":"128.6375448","y":"35.90084998","addr":"대구 동구 불로동 815-4","region":"동구","fid":2},{"num":670,"x":"128.6362876","y":"35.90459893","addr":"대구 동구 불로동 847-1","region":"동구","fid":2},{"num":671,"x":"128.6358909","y":"35.90265934","addr":"대구 동구 불로동 797","region":"동구","fid":2},{"num":672,"x":"128.6345629","y":"35.90524191","addr":"대구 동구 불로동 631-5","region":"동구","fid":2},{"num":673,"x":"128.6312613","y":"35.8881578","addr":"대구 동구 신암동 133-7","region":"동구","fid":2},{"num":674,"x":"128.6297802","y":"35.88543968","addr":"대구 동구 신암동 136-92","region":"동구","fid":2},{"num":675,"x":"128.667065","y":"35.92516947","addr":"대구 동구 도동 산 187-12","region":"동구","fid":2},{"num":676,"x":"128.6644089","y":"35.92529499","addr":"대구 동구 도동 산 171-2","region":"동구","fid":2},{"num":677,"x":"128.6718999","y":"35.92762713","addr":"대구 동구 도동 559-5","region":"동구","fid":2},{"num":678,"x":"128.6711475","y":"35.92598631","addr":"대구 동구 도동 561-2","region":"동구","fid":2},{"num":679,"x":"128.6790707","y":"35.92946456","addr":"대구 동구 도동 산 34","region":"동구","fid":2},{"num":680,"x":"128.6341912","y":"35.87334765","addr":"대구 동구 신천동 497-29","region":"동구","fid":2},{"num":681,"x":"128.635134","y":"35.8738163","addr":"대구 동구 신천동 491-2","region":"동구","fid":2},{"num":682,"x":"128.6366017","y":"35.87418156","addr":"대구 동구 신천동 484-13","region":"동구","fid":2},{"num":683,"x":"128.632486","y":"35.87434859","addr":"대구 동구 신천동 448-44","region":"동구","fid":2},{"num":684,"x":"128.6865876","y":"35.87824406","addr":"대구 동구 신평동 593","region":"동구","fid":2},{"num":685,"x":"128.6945549","y":"35.95625988","addr":"대구 동구 백안동 467-2","region":"동구","fid":2},{"num":686,"x":"128.6972287","y":"35.88401306","addr":"대구 동구 신평동 122","region":"동구","fid":2},{"num":687,"x":"128.706128","y":"35.96082301","addr":"대구 동구 백안동 5","region":"동구","fid":2},{"num":688,"x":"128.7095402","y":"35.93597504","addr":"대구 동구 평광동 산 64","region":"동구","fid":2},{"num":689,"x":"128.6871152","y":"35.87395546","addr":"대구 동구 용계동 613-27","region":"동구","fid":2},{"num":690,"x":"128.6955672","y":"35.87352717","addr":"대구 동구 용계동 730-16","region":"동구","fid":2},{"num":691,"x":"128.7098795","y":"35.87027929","addr":"대구 동구 신기동 40","region":"동구","fid":2},{"num":692,"x":"128.7174617","y":"35.86615703","addr":"대구 동구 동호동 206-2","region":"동구","fid":2},{"num":693,"x":"128.7418122","y":"35.96506115","addr":"대구 동구 능성동 156-1","region":"동구","fid":2},{"num":694,"x":"128.6962346","y":"35.95558616","addr":"대구 동구 백안동 755-1","region":"동구","fid":2},{"num":695,"x":"128.6487518","y":"35.91085086","addr":"대구 동구 도동 20-30","region":"동구","fid":2},{"num":696,"x":"128.650358","y":"35.91048146","addr":"대구 동구 도동 80-6","region":"동구","fid":2},{"num":697,"x":"128.6521283","y":"35.90999031","addr":"대구 동구 도동 978-48","region":"동구","fid":2},{"num":698,"x":"128.7034757","y":"35.87585269","addr":"대구 동구 율암동 394-5","region":"동구","fid":2},{"num":699,"x":"128.6222261","y":"35.87559403","addr":"대구 동구 신천동 22-2","region":"동구","fid":2},{"num":700,"x":"128.6953638","y":"35.95443348","addr":"대구 동구 백안동 755-1","region":"동구","fid":2},{"num":701,"x":"128.6968925","y":"35.95354403","addr":"대구 동구 백안동 255","region":"동구","fid":2},{"num":702,"x":"128.6423504","y":"35.87702128","addr":"대구 동구 효목동 564-1","region":"동구","fid":2},{"num":703,"x":"128.7190887","y":"35.86723786","addr":"대구 동구 동호동 109-6","region":"동구","fid":2},{"num":704,"x":"128.6997913","y":"35.86983978","addr":"대구 동구 율하동 900","region":"동구","fid":2},{"num":705,"x":"128.7044095","y":"35.87531376","addr":"대구 동구 율암동 394-4","region":"동구","fid":2},{"num":706,"x":"128.7066778","y":"35.86978136","addr":"대구 동구 신기동 268-9","region":"동구","fid":2},{"num":707,"x":"128.7129568","y":"35.87014528","addr":"대구 동구 서호동 44-1","region":"동구","fid":2},{"num":708,"x":"128.7365711","y":"35.87061976","addr":"대구 동구 괴전동 169","region":"동구","fid":2},{"num":709,"x":"128.6901522","y":"35.89996838","addr":"대구 동구 둔산동 147","region":"동구","fid":2},{"num":710,"x":"128.6902031","y":"35.93458959","addr":"대구 동구 평광동 1238","region":"동구","fid":2},{"num":711,"x":"128.6997918","y":"35.8712252","addr":"대구 동구 율하동 77","region":"동구","fid":2},{"num":712,"x":"128.714212","y":"35.87027192","addr":"대구 동구 서호동 20-1","region":"동구","fid":2},{"num":713,"x":"128.64271","y":"35.91501542","addr":"대구 동구 불로동 286","region":"동구","fid":2},{"num":714,"x":"128.671639","y":"35.95794949","addr":"대구 동구 미대동 111-1","region":"동구","fid":2},{"num":715,"x":"128.6901447","y":"35.86382447","addr":"대구 동구 율하동 684-1","region":"동구","fid":2},{"num":716,"x":"128.7108511","y":"35.87179003","addr":"대구 동구 신기동 21-2","region":"동구","fid":2},{"num":717,"x":"128.6498525","y":"35.88791768","addr":"대구 동구 검사동 1024-31","region":"동구","fid":2},{"num":718,"x":"128.6502767","y":"35.98136936","addr":"대구 동구 신용동 696","region":"동구","fid":2},{"num":719,"x":"128.7044331","y":"35.86304295","addr":"대구 동구 율하동 1492","region":"동구","fid":2},{"num":720,"x":"128.7139074","y":"35.87331484","addr":"대구 동구 각산동 905","region":"동구","fid":2},{"num":721,"x":"128.6740722","y":"35.89774256","addr":"대구 동구 둔산동 1036","region":"동구","fid":2},{"num":722,"x":"128.6842817","y":"35.97195003","addr":"대구 동구 용수동 332","region":"동구","fid":2},{"num":723,"x":"128.7149553","y":"35.8737471","addr":"대구 동구 각산동 383-6","region":"동구","fid":2},{"num":724,"x":"128.6398162","y":"35.88556062","addr":"대구 동구 효목동 55","region":"동구","fid":2},{"num":725,"x":"128.7207037","y":"35.87559579","addr":"대구 동구 각산동 425","region":"동구","fid":2},{"num":726,"x":"128.6429012","y":"35.87407766","addr":"대구 동구 효목동 647","region":"동구","fid":2},{"num":727,"x":"128.6510286","y":"35.98220515","addr":"대구 동구 신용동 595","region":"동구","fid":2},{"num":728,"x":"128.6521896","y":"35.88956044","addr":"대구 동구 입석동 925-17","region":"동구","fid":2},{"num":729,"x":"128.6157824","y":"35.88195797","addr":"대구 동구 신암동 812-14","region":"동구","fid":2},{"num":730,"x":"128.6182088","y":"35.86827924","addr":"대구 동구 신천동 824-10","region":"동구","fid":2},{"num":731,"x":"128.6514069","y":"35.89338461","addr":"대구 동구 입석동 854-6","region":"동구","fid":2},{"num":732,"x":"128.6249117","y":"35.88518834","addr":"대구 동구 신암동 611-3","region":"동구","fid":2},{"num":733,"x":"128.6429039","y":"35.87840399","addr":"대구 동구 효목동 352-27","region":"동구","fid":2},{"num":734,"x":"128.6460656","y":"35.91516","addr":"대구 동구 불로동 324-2","region":"동구","fid":2},{"num":736,"x":"128.6470571","y":"35.93083712"},{"num":736,"x":"128.6479822","y":"35.92204903","addr":"대구 동구 봉무동 1358-2","region":"동구","fid":2},{"num":737,"x":"128.6181347","y":"35.99549151","addr":"대구 동구 덕곡동 146","region":"동구","fid":2},{"num":738,"x":"128.696825","y":"35.87129479","addr":"대구 동구 율하동 41","region":"동구","fid":2},{"num":739,"x":"128.6842974","y":"35.87784588","addr":"대구 동구 용계동 887-87","region":"동구","fid":2},{"num":740,"x":"128.6832683","y":"35.87687106","addr":"대구 동구 용계동 1008-1","region":"동구","fid":2},{"num":741,"x":"128.7577717","y":"35.87020132","addr":"대구 동구 사복동 220","region":"동구","fid":2},{"num":742,"x":"128.71194","y":"35.8767972","addr":"대구 동구 각산동 1014-6","region":"동구","fid":2},{"num":743,"x":"128.6238052","y":"35.9841178","addr":"대구 동구 덕곡동 572","region":"동구","fid":2},{"num":744,"x":"128.7552632","y":"35.87474016","addr":"대구 동구 사복동 852","region":"동구","fid":2},{"num":745,"x":"128.753766","y":"35.87493566","addr":"대구 동구 사복동 859","region":"동구","fid":2},{"num":746,"x":"128.7022234","y":"35.87871943","addr":"대구 동구 용계동 5","region":"동구","fid":2},{"num":747,"x":"128.7525714","y":"35.85809429","addr":"대구 동구 금강동 833-16","region":"동구","fid":2},{"num":748,"x":"128.7126982","y":"35.86286831","addr":"대구 동구 서호동 312-12","region":"동구","fid":2},{"num":749,"x":"128.6624753","y":"35.88118158","addr":"대구 동구 방촌동 1050-71","region":"동구","fid":2},{"num":750,"x":"128.6879675","y":"35.88846508","addr":"대구 동구 부동 286-4","region":"동구","fid":2},{"num":751,"x":"128.6881457","y":"35.95927092","addr":"대구 동구 미곡동 267","region":"동구","fid":2},{"num":752,"x":"128.6887893","y":"35.95799358","addr":"대구 동구 미곡동 234","region":"동구","fid":2},{"num":753,"x":"128.6897591","y":"35.90773967","addr":"대구 동구 둔산동 386","region":"동구","fid":2},{"num":754,"x":"128.6527781","y":"35.88707639","addr":"대구 동구 검사동 990-82","region":"동구","fid":2},{"num":755,"x":"128.65423","y":"35.97083676","addr":"대구 동구 내동 313","region":"동구","fid":2},{"num":756,"x":"128.6752841","y":"35.98753934","addr":"대구 동구 신무동 199","region":"동구","fid":2},{"num":757,"x":"128.6220717","y":"35.9950316","addr":"대구 동구 송정동 615","region":"동구","fid":2},{"num":758,"x":"128.6479526","y":"35.9318477","addr":"대구 동구 봉무동 207","region":"동구","fid":2},{"num":759,"x":"128.7071203","y":"35.87829041","addr":"대구 동구 율암동 318","region":"동구","fid":2},{"num":760,"x":"128.7579177","y":"35.88206322","addr":"대구 동구 숙천동 109","region":"동구","fid":2},{"num":761,"x":"128.6486359","y":"35.92324835","addr":"대구 동구 봉무동 388-3","region":"동구","fid":2},{"num":762,"x":"128.6508379","y":"35.88750183","addr":"대구 동구 검사동 1022-18","region":"동구","fid":2},{"num":763,"x":"128.6393574","y":"35.94247904","addr":"대구 동구 지묘동 768-1","region":"동구","fid":2},{"num":764,"x":"128.6489871","y":"35.88273397","addr":"대구 동구 효목동 212","region":"동구","fid":2},{"num":765,"x":"128.6453573","y":"35.89391733","addr":"대구 동구 지저동 801-14","region":"동구","fid":2},{"num":766,"x":"128.6400376","y":"35.896418","addr":"대구 동구 지저동 694-8","region":"동구","fid":2},{"num":767,"x":"128.716638","y":"35.88620053","addr":"대구 동구 각산동 1026-11","region":"동구","fid":2},{"num":768,"x":"128.7232162","y":"35.88661114","addr":"대구 동구 각산동 1124","region":"동구","fid":2},{"num":769,"x":"128.6143205","y":"35.88017029","addr":"대구 동구 신암동 1186-13","region":"동구","fid":2},{"num":770,"x":"128.6420928","y":"35.89408425","addr":"대구 동구 지저동 829-7","region":"동구","fid":2},{"num":771,"x":"128.6485685","y":"35.87995828","addr":"대구 동구 효목동 187-10","region":"동구","fid":2},{"num":772,"x":"128.6524406","y":"35.88183365","addr":"대구 동구 효목동 980","region":"동구","fid":2},{"num":773,"x":"128.7485587","y":"35.87289476","addr":"대구 동구 대림동 887","region":"동구","fid":2},{"num":774,"x":"128.7104847","y":"35.87692071","addr":"대구 동구 율암동 352-5","region":"동구","fid":2},{"num":775,"x":"128.7128661","y":"35.86752771","addr":"대구 동구 서호동 115-4","region":"동구","fid":2},{"num":776,"x":"128.729055","y":"35.87284032","addr":"대구 동구 신서동 823-70","region":"동구","fid":2},{"num":777,"x":"128.7371478","y":"35.87340203","addr":"대구 동구 괴전동 117-20","region":"동구","fid":2},{"num":778,"x":"128.6743629","y":"35.95748664","addr":"대구 동구 미대동 761","region":"동구","fid":2},{"num":779,"x":"128.682092","y":"35.95268625","addr":"대구 동구 미대동 750","region":"동구","fid":2},{"num":780,"x":"128.6952879","y":"35.88107434","addr":"대구 동구 신평동 168-3","region":"동구","fid":2},{"num":781,"x":"128.6982915","y":"35.87162198","addr":"대구 동구 율하동 254-1","region":"동구","fid":2},{"num":782,"x":"128.7016522","y":"35.93326918","addr":"대구 동구 평광동 1612","region":"동구","fid":2},{"num":783,"x":"128.707144","y":"35.96583378","addr":"대구 동구 도학동 516","region":"동구","fid":2},{"num":784,"x":"128.6643413","y":"35.88683572","addr":"대구 동구 검사동 1074-2","region":"동구","fid":2},{"num":785,"x":"128.6677868","y":"35.88022907","addr":"대구 동구 방촌동 1084-123","region":"동구","fid":2},{"num":786,"x":"128.666242","y":"35.87820844","addr":"대구 동구 방촌동 1084-38","region":"동구","fid":2},{"num":787,"x":"128.7117958","y":"35.95162771","addr":"대구 동구 진인동 743","region":"동구","fid":2},{"num":788,"x":"128.6195082","y":"35.88266926","addr":"대구 동구 신암동 770-6","region":"동구","fid":2},{"num":789,"x":"128.6615282","y":"35.8839434","addr":"대구 동구 방촌동 1012-14","region":"동구","fid":2},{"num":790,"x":"128.6626324","y":"35.88424096","addr":"대구 동구 방촌동 1010-53","region":"동구","fid":2},{"num":791,"x":"128.6656846","y":"35.88157451","addr":"대구 동구 방촌동 1071-7","region":"동구","fid":2},{"num":792,"x":"128.6672837","y":"35.88250072","addr":"대구 동구 방촌동 907-7","region":"동구","fid":2},{"num":793,"x":"128.7135042","y":"35.87489525","addr":"대구 동구 각산동 905","region":"동구","fid":2},{"num":794,"x":"128.71974","y":"35.87506986","addr":"대구 동구 각산동 400","region":"동구","fid":2},{"num":795,"x":"128.6420935","y":"35.9300801","addr":"대구 동구 봉무동 972-4","region":"동구","fid":2},{"num":796,"x":"128.6931969","y":"35.89837144","addr":"대구 동구 둔산동 76-8","region":"동구","fid":2},{"num":797,"x":"128.6255114","y":"35.98768983","addr":"대구 동구 송정동 284","region":"동구","fid":2},{"num":798,"x":"128.6203766","y":"35.98481865","addr":"대구 동구 덕곡동 530-2","region":"동구","fid":2},{"num":799,"x":"128.6844439","y":"35.96460888","addr":"대구 동구 미곡동 400-3","region":"동구","fid":2},{"num":800,"x":"128.6913743","y":"35.95684293","addr":"대구 동구 백안동 655","region":"동구","fid":2},{"num":801,"x":"128.7058671","y":"35.8741385","addr":"대구 동구 율암동 431-6","region":"동구","fid":2},{"num":802,"x":"128.7077384","y":"35.87370474","addr":"대구 동구 율암동 431-4","region":"동구","fid":2},{"num":803,"x":"128.6618742","y":"35.88721175","addr":"대구 동구 검사동 756-106","region":"동구","fid":2},{"num":804,"x":"128.6741418","y":"35.87894077","addr":"대구 동구 방촌동 1113-128","region":"동구","fid":2},{"num":805,"x":"128.6482344","y":"35.91301421","addr":"대구 동구 불로동 산 12","region":"동구","fid":2},{"num":806,"x":"128.6609058","y":"35.88515578","addr":"대구 동구 검사동 756-128","region":"동구","fid":2},{"num":807,"x":"128.7338647","y":"35.86895702","addr":"대구 동구 신서동 553-14","region":"동구","fid":2},{"num":808,"x":"128.7346769","y":"35.86382529","addr":"대구 동구 신서동 525-24","region":"동구","fid":2},{"num":809,"x":"128.7433341","y":"35.96567572","addr":"대구 동구 능성동 178","region":"동구","fid":2},{"num":810,"x":"128.6219115","y":"35.99222128","addr":"대구 동구 송정동 667","region":"동구","fid":2},{"num":811,"x":"128.6537465","y":"35.88753986","addr":"대구 동구 검사동 994-49","region":"동구","fid":2},{"num":812,"x":"128.648377","y":"35.89208627","addr":"대구 동구 입석동 932-11","region":"동구","fid":2},{"num":813,"x":"128.7156234","y":"35.86705943","addr":"대구 동구 서호동 197-12","region":"동구","fid":2},{"num":814,"x":"128.6602233","y":"35.88232216","addr":"대구 동구 방촌동 1018-31","region":"동구","fid":2},{"num":815,"x":"128.6714324","y":"35.95254844","addr":"대구 동구 미대동 702","region":"동구","fid":2},{"num":816,"x":"128.6735635","y":"35.98852008","addr":"대구 동구 신무동 645-4","region":"동구","fid":2},{"num":817,"x":"128.677384","y":"35.90372437","addr":"대구 동구 둔산동 산 121-5","region":"동구","fid":2},{"num":818,"x":"128.7062418","y":"35.87142955","addr":"대구 동구 신기동 184-22","region":"동구","fid":2},{"num":819,"x":"128.6249841","y":"35.9857625","addr":"대구 동구 송정동 240-3","region":"동구","fid":2},{"num":820,"x":"128.7416581","y":"35.85872275","addr":"대구 동구 금강동 840-12","region":"동구","fid":2},{"num":821,"x":"128.7428003","y":"35.88027948","addr":"대구 동구 동내동 275-1","region":"동구","fid":2},{"num":823,"x":"128.7175752","y":"35.86779671"},{"num":823,"x":"128.7425585","y":"35.88538033","addr":"대구 동구 동내동 1137","region":"동구","fid":2},{"num":824,"x":"128.6521572","y":"35.89187495","addr":"대구 동구 입석동 888-13","region":"동구","fid":2},{"num":825,"x":"128.6597846","y":"35.88591442","addr":"대구 동구 검사동 950-28","region":"동구","fid":2},{"num":826,"x":"128.6974839","y":"35.88248674","addr":"대구 동구 신평동 46","region":"동구","fid":2},{"num":827,"x":"128.6648589","y":"35.88434708","addr":"대구 동구 방촌동 988-18","region":"동구","fid":2},{"num":828,"x":"128.6658492","y":"35.88556291","addr":"대구 동구 방촌동 987-25","region":"동구","fid":2},{"num":829,"x":"128.6694122","y":"35.88251671","addr":"대구 동구 방촌동 890-45","region":"동구","fid":2},{"num":830,"x":"128.6704131","y":"35.88028825","addr":"대구 동구 방촌동 1139-1","region":"동구","fid":2},{"num":831,"x":"128.6704914","y":"35.88223631","addr":"대구 동구 방촌동 806-5","region":"동구","fid":2},{"num":832,"x":"128.7422104","y":"35.85984658","addr":"대구 동구 금강동 424","region":"동구","fid":2},{"num":833,"x":"128.635334","y":"35.8803332","addr":"대구 동구 신암동 294","region":"동구","fid":2},{"num":834,"x":"128.6363588","y":"35.8794121","addr":"대구 동구 효목동 283-3","region":"동구","fid":2},{"num":835,"x":"128.6357781","y":"35.87086229","addr":"대구 동구 신천동 743","region":"동구","fid":2},{"num":836,"x":"128.6290202","y":"35.86731406","addr":"대구 동구 신천동 742","region":"동구","fid":2},{"num":837,"x":"128.6210009","y":"35.87847789","addr":"대구 동구 신암동 186-8","region":"동구","fid":2},{"num":838,"x":"128.6443953","y":"35.88556969","addr":"대구 동구 효목동 89-24","region":"동구","fid":2},{"num":839,"x":"128.6313311","y":"35.8731549","addr":"대구 동구 신천동 743","region":"동구","fid":2},{"num":840,"x":"128.6289532","y":"35.87435211","addr":"대구 동구 신천동 290-5","region":"동구","fid":2},{"num":841,"x":"128.6299696","y":"35.86832424","addr":"대구 동구 신천동 302-1","region":"동구","fid":2},{"num":842,"x":"128.6301855","y":"35.87338348","addr":"대구 동구 신천동 322-2","region":"동구","fid":2},{"num":843,"x":"128.6300249","y":"35.87477314","addr":"대구 동구 신천동 326-21","region":"동구","fid":2},{"num":844,"x":"128.6331709","y":"35.86930941","addr":"대구 동구 신천동 353-20","region":"동구","fid":2},{"num":845,"x":"128.6506288","y":"35.87901116","addr":"대구 동구 효목동 209","region":"동구","fid":2},{"num":846,"x":"128.646754","y":"35.88320228","addr":"대구 동구 효목동 136-23","region":"동구","fid":2},{"num":847,"x":"128.6360251","y":"35.8864596","addr":"대구 동구 신암동 106-77","region":"동구","fid":2},{"num":848,"x":"128.6379528","y":"35.89062331","addr":"대구 동구 신암동 1313-4","region":"동구","fid":2},{"num":849,"x":"128.6315349","y":"35.8688229","addr":"대구 동구 신천동 313-6","region":"동구","fid":2},{"num":850,"x":"128.6439679","y":"35.88453794","addr":"대구 동구 효목동 119-7","region":"동구","fid":2},{"num":851,"x":"128.64215","y":"35.88654336","addr":"대구 동구 효목동 82-21","region":"동구","fid":2},{"num":852,"x":"128.7012737","y":"35.86433761","addr":"대구 동구 율하동 1466","region":"동구","fid":2},{"num":853,"x":"128.6339769","y":"35.87852733","addr":"대구 동구 효목동 647","region":"동구","fid":2},{"num":854,"x":"128.6412159","y":"35.87828137","addr":"대구 동구 효목동 367-7","region":"동구","fid":2},{"num":855,"x":"128.6392631","y":"35.88913152","addr":"대구 동구 신암동 54-82","region":"동구","fid":2},{"num":856,"x":"128.6442951","y":"35.90749156","addr":"대구 동구 지저동 204-1","region":"동구","fid":2},{"num":857,"x":"128.6433892","y":"35.87716602","addr":"대구 동구 효목동 647","region":"동구","fid":2},{"num":858,"x":"128.6462968","y":"35.87598381","addr":"대구 동구 효목동 647","region":"동구","fid":2},{"num":859,"x":"128.6346109","y":"35.88287207","addr":"대구 동구 신암동 355-14","region":"동구","fid":2},{"num":860,"x":"128.6304544","y":"35.87026671","addr":"대구 동구 신천동 316-5","region":"동구","fid":2},{"num":861,"x":"128.702505","y":"35.86395321","addr":"대구 동구 율하동 1467","region":"동구","fid":2},{"num":862,"x":"128.6395952","y":"35.88715625","addr":"대구 동구 신암동 1463","region":"동구","fid":2},{"num":863,"x":"128.6404287","y":"35.89252013","addr":"대구 동구 지저동 838-7","region":"동구","fid":2},{"num":864,"x":"128.6503281","y":"35.88133387","addr":"대구 동구 효목동 산 234-51","region":"동구","fid":2},{"num":865,"x":"128.6538476","y":"35.8813496","addr":"대구 동구 효목동 1010-15","region":"동구","fid":2},{"num":866,"x":"128.6976453","y":"35.93124381","addr":"대구 동구 평광동 609-3","region":"동구","fid":2},{"num":867,"x":"128.6404069","y":"35.87738389","addr":"대구 동구 효목동 450-5","region":"동구","fid":2},{"num":868,"x":"128.675194","y":"35.91542787","addr":"대구 동구 도동 727","region":"동구","fid":2},{"num":869,"x":"128.6448028","y":"35.89059641","addr":"대구 동구 입석동 999-6","region":"동구","fid":2},{"num":870,"x":"128.637922","y":"35.8944505","addr":"대구 동구 지저동 726-2","region":"동구","fid":2},{"num":871,"x":"128.6333387","y":"35.9031952","addr":"대구 동구 불로동 1107-1","region":"동구","fid":2},{"num":872,"x":"128.6347276","y":"35.90626462","addr":"대구 동구 불로동 631-5","region":"동구","fid":2},{"num":873,"x":"128.674959","y":"35.91424883","addr":"대구 동구 도동 산 63","region":"동구","fid":2},{"num":874,"x":"128.6370241","y":"35.90368079","addr":"대구 동구 불로동 789-1","region":"동구","fid":2},{"num":875,"x":"128.6413251","y":"35.90588505","addr":"대구 동구 불로동 721","region":"동구","fid":2},{"num":876,"x":"128.6759795","y":"35.91728387","addr":"대구 동구 도동 산 56","region":"동구","fid":2},{"num":877,"x":"128.7064569","y":"35.86326424","addr":"대구 동구 율하동 1568","region":"동구","fid":2},{"num":878,"x":"128.6872354","y":"35.86855772","addr":"대구 동구 용계동 855-2","region":"동구","fid":2},{"num":879,"x":"128.6190315","y":"35.88547693","addr":"대구 동구 신암동 708-211","region":"동구","fid":2},{"num":880,"x":"128.7033222","y":"35.86819496","addr":"대구 동구 율하동 953-7","region":"동구","fid":2},{"num":881,"x":"128.7046423","y":"35.86941262","addr":"대구 동구 율하동 948","region":"동구","fid":2},{"num":882,"x":"128.6246469","y":"35.88310714","addr":"대구 동구 신암동 588-11","region":"동구","fid":2},{"num":883,"x":"128.6246541","y":"35.88134973","addr":"대구 동구 신암동 223-43","region":"동구","fid":2},{"num":884,"x":"128.6222005","y":"35.88899037","addr":"대구 동구 신암동 668-9","region":"동구","fid":2},{"num":885,"x":"128.6235294","y":"35.88188331","addr":"대구 동구 신암동 215-8","region":"동구","fid":2},{"num":886,"x":"128.6850094","y":"35.87446422","addr":"대구 동구 용계동 551","region":"동구","fid":2},{"num":887,"x":"128.699561","y":"35.868258","addr":"대구 동구 율하동 975-1","region":"동구","fid":2},{"num":888,"x":"128.7058311","y":"35.87814181","addr":"대구 동구 율암동 313-2","region":"동구","fid":2},{"num":889,"x":"128.703863","y":"35.88081888","addr":"대구 동구 율암동 524-175","region":"동구","fid":2},{"num":890,"x":"128.7019872","y":"35.86988138","addr":"대구 동구 율하동 921-12","region":"동구","fid":2},{"num":891,"x":"128.6997458","y":"35.86605565","addr":"대구 동구 율하동 1018","region":"동구","fid":2},{"num":892,"x":"128.7054229","y":"35.87063013","addr":"대구 동구 신기동 197-9","region":"동구","fid":2},{"num":893,"x":"128.7102494","y":"35.8690556","addr":"대구 동구 신기동 589-1","region":"동구","fid":2},{"num":894,"x":"128.7152013","y":"35.86957451","addr":"대구 동구 동호동 95-2","region":"동구","fid":2},{"num":895,"x":"128.7034409","y":"35.87075728","addr":"대구 동구 율하동 172-10","region":"동구","fid":2},{"num":896,"x":"128.7143843","y":"35.87160491","addr":"대구 동구 동호동 40","region":"동구","fid":2},{"num":897,"x":"128.6402602","y":"35.8837323","addr":"대구 동구 효목동 54-5","region":"동구","fid":2},{"num":898,"x":"128.7186648","y":"35.87361098","addr":"대구 동구 각산동 1177","region":"동구","fid":2},{"num":899,"x":"128.7124724","y":"35.87110393","addr":"대구 동구 서호동 7-8","region":"동구","fid":2},{"num":900,"x":"128.7207824","y":"35.86987976","addr":"대구 동구 각산동 293-1","region":"동구","fid":2},{"num":901,"x":"128.7023386","y":"35.87421774","addr":"대구 동구 율암동 1156-2","region":"동구","fid":2},{"num":902,"x":"128.6953056","y":"35.86318911","addr":"대구 동구 율하동 1300","region":"동구","fid":2},{"num":903,"x":"128.6939888","y":"35.86420782","addr":"대구 동구 율하동 1302","region":"동구","fid":2},{"num":904,"x":"128.6446904","y":"35.91090611","addr":"대구 동구 불로동 578-4","region":"동구","fid":2},{"num":905,"x":"128.6441544","y":"35.91221851","addr":"대구 동구 불로동 390-4","region":"동구","fid":2},{"num":906,"x":"128.6441246","y":"35.90993692","addr":"대구 동구 불로동 1182","region":"동구","fid":2},{"num":907,"x":"128.6613833","y":"35.88120914","addr":"대구 동구 방촌동 1047-4","region":"동구","fid":2},{"num":908,"x":"128.6399803","y":"35.98854792","addr":"대구 동구 중대동 1168","region":"동구","fid":2},{"num":909,"x":"128.7058491","y":"35.99179517","addr":"대구 동구 도학동 35","region":"동구","fid":2},{"num":910,"x":"128.6432745","y":"35.91140592","addr":"대구 동구 불로동 401-2","region":"동구","fid":2},{"num":911,"x":"128.6437359","y":"35.89330709","addr":"대구 동구 지저동 794-25","region":"동구","fid":2},{"num":912,"x":"128.6434614","y":"35.92737432","addr":"대구 동구 봉무동 1519","region":"동구","fid":2},{"num":913,"x":"128.7164244","y":"35.96037312","addr":"대구 동구 진인동 228","region":"동구","fid":2},{"num":914,"x":"128.6403516","y":"35.89507317","addr":"대구 동구 지저동 770-6","region":"동구","fid":2},{"num":915,"x":"128.6414912","y":"35.89567712","addr":"대구 동구 지저동 691-45","region":"동구","fid":2},{"num":916,"x":"128.6387737","y":"35.89590468","addr":"대구 동구 지저동 715-6","region":"동구","fid":2},{"num":917,"x":"128.6155529","y":"35.87998966","addr":"대구 동구 신암동 483-3","region":"동구","fid":2},{"num":918,"x":"128.6354771","y":"35.89926214","addr":"대구 동구 불로동 1000-32","region":"동구","fid":2},{"num":919,"x":"128.6413647","y":"35.91196686","addr":"대구 동구 불로동 305-1","region":"동구","fid":2},{"num":920,"x":"128.6437818","y":"35.91564306","addr":"대구 동구 불로동 1166","region":"동구","fid":2},{"num":921,"x":"128.6472462","y":"35.90795272","addr":"대구 동구 지저동 173-1","region":"동구","fid":2},{"num":922,"x":"128.6473858","y":"35.90938953","addr":"대구 동구 도동 3-22","region":"동구","fid":2},{"num":923,"x":"128.6424322","y":"35.91335715","addr":"대구 동구 불로동 1157-5","region":"동구","fid":2},{"num":924,"x":"128.6447689","y":"35.89689769","addr":"대구 동구 지저동 907","region":"동구","fid":2},{"num":925,"x":"128.6780865","y":"35.9307047","addr":"대구 동구 도동 산 10","region":"동구","fid":2},{"num":926,"x":"128.6738502","y":"35.93144094","addr":"대구 동구 도동 산 26","region":"동구","fid":2},{"num":927,"x":"128.6883006","y":"35.8998296","addr":"대구 동구 둔산동 237","region":"동구","fid":2},{"num":928,"x":"128.6392297","y":"35.98538695","addr":"대구 동구 중대동 764","region":"동구","fid":2},{"num":929,"x":"128.6371946","y":"35.89561709","addr":"대구 동구 불로동 1063-42","region":"동구","fid":2},{"num":930,"x":"128.6360041","y":"35.89566005","addr":"대구 동구 불로동 1063-22","region":"동구","fid":2},{"num":931,"x":"128.6457657","y":"35.91258311","addr":"대구 동구 불로동 495-4","region":"동구","fid":2},{"num":932,"x":"128.6577345","y":"35.88814113","addr":"대구 동구 검사동 908-39","region":"동구","fid":2},{"num":933,"x":"128.691566","y":"35.86160174","addr":"대구 동구 율하동 1300","region":"동구","fid":2},{"num":934,"x":"128.6931928","y":"35.86551708","addr":"대구 동구 율하동 1242","region":"동구","fid":2},{"num":935,"x":"128.6702369","y":"35.9243433","addr":"대구 동구 도동 533-2","region":"동구","fid":2},{"num":936,"x":"128.6920193","y":"35.862904","addr":"대구 동구 율하동 1311","region":"동구","fid":2},{"num":937,"x":"128.6407544","y":"35.98619005","addr":"대구 동구 중대동 114","region":"동구","fid":2},{"num":938,"x":"128.6979709","y":"35.86867928","addr":"대구 동구 율하동 1003-5","region":"동구","fid":2},{"num":939,"x":"128.6471014","y":"35.89419983","addr":"대구 동구 입석동 970-3","region":"동구","fid":2},{"num":940,"x":"128.687163","y":"35.87689833","addr":"대구 동구 용계동 369-2","region":"동구","fid":2},{"num":941,"x":"128.6447059","y":"35.89230483","addr":"대구 동구 지저동 819-31","region":"동구","fid":2},{"num":942,"x":"128.6508359","y":"35.90941461","addr":"대구 동구 도동 89-2","region":"동구","fid":2},{"num":943,"x":"128.6425217","y":"35.91073288","addr":"대구 동구 불로동 420","region":"동구","fid":2},{"num":944,"x":"128.6458562","y":"35.90703772","addr":"대구 동구 지저동 230-3","region":"동구","fid":2},{"num":945,"x":"128.6488121","y":"35.90746398","addr":"대구 동구 지저동 164","region":"동구","fid":2},{"num":946,"x":"128.6451057","y":"35.91351917","addr":"대구 동구 불로동 30-1","region":"동구","fid":2},{"num":947,"x":"128.6993601","y":"35.86415441","addr":"대구 동구 율하동 1464","region":"동구","fid":2},{"num":948,"x":"128.6442216","y":"35.914392","addr":"대구 동구 불로동 1148-4","region":"동구","fid":2},{"num":949,"x":"128.7601331","y":"35.86955426","addr":"대구 동구 사복동 461-2","region":"동구","fid":2},{"num":950,"x":"128.7455612","y":"35.85492181","addr":"대구 동구 금강동 195-2","region":"동구","fid":2},{"num":951,"x":"128.742125","y":"35.96375872","addr":"대구 동구 능성동 137-1","region":"동구","fid":2},{"num":952,"x":"128.7331379","y":"35.96628882","addr":"대구 동구 능성동 산 114","region":"동구","fid":2},{"num":953,"x":"128.6935511","y":"35.99111317","addr":"대구 동구 용수동 89-1","region":"동구","fid":2},{"num":954,"x":"128.674852","y":"35.98572026","addr":"대구 동구 신무동 676-10","region":"동구","fid":2},{"num":955,"x":"128.6226728","y":"35.9845259","addr":"대구 동구 덕곡동 556","region":"동구","fid":2},{"num":956,"x":"128.6972316","y":"35.9548987","addr":"대구 동구 백안동 223-1","region":"동구","fid":2},{"num":957,"x":"128.6559094","y":"35.88059353","addr":"대구 동구 효목동 1091","region":"동구","fid":2},{"num":958,"x":"128.6466822","y":"35.89523418","addr":"대구 동구 지저동 645-19","region":"동구","fid":2},{"num":959,"x":"128.6393019","y":"35.9088342","addr":"대구 동구 불로동 669","region":"동구","fid":2},{"num":960,"x":"128.6434917","y":"35.89680068","addr":"대구 동구 지저동 663-21","region":"동구","fid":2},{"num":961,"x":"128.6381036","y":"35.89922163","addr":"대구 동구 지저동 459","region":"동구","fid":2},{"num":962,"x":"128.6505936","y":"35.89125392","addr":"대구 동구 입석동 932-180","region":"동구","fid":2},{"num":963,"x":"128.6571403","y":"35.88444615","addr":"대구 동구 검사동 960-168","region":"동구","fid":2},{"num":964,"x":"128.6711629","y":"35.88344863","addr":"대구 동구 방촌동 798-28","region":"동구","fid":2},{"num":965,"x":"128.6849003","y":"35.89717584","addr":"대구 동구 둔산동 263-1","region":"동구","fid":2},{"num":966,"x":"128.6756293","y":"35.91053294","addr":"대구 동구 둔산동 795-1","region":"동구","fid":2},{"num":967,"x":"128.6462241","y":"35.9141486","addr":"대구 동구 불로동 365-5","region":"동구","fid":2},{"num":968,"x":"128.6417627","y":"35.91584213","addr":"대구 동구 불로동 1282","region":"동구","fid":2},{"num":969,"x":"128.6414865","y":"35.88231679","addr":"대구 동구 효목동 49-44","region":"동구","fid":2},{"num":970,"x":"128.6250236","y":"35.8703023","addr":"대구 동구 신천동 741","region":"동구","fid":2},{"num":971,"x":"128.6435454","y":"35.89179794","addr":"대구 동구 지저동 866-1","region":"동구","fid":2},{"num":972,"x":"128.6396087","y":"35.87502822","addr":"대구 동구 효목동 434-4","region":"동구","fid":2},{"num":973,"x":"128.6279776","y":"35.87541286","addr":"대구 동구 신천동 742","region":"동구","fid":2},{"num":974,"x":"128.6578159","y":"35.8766912","addr":"대구 동구 효목동 1214-3","region":"동구","fid":2},{"num":975,"x":"128.643619","y":"35.8749639","addr":"대구 동구 효목동 626","region":"동구","fid":2},{"num":976,"x":"128.6336751","y":"35.87185695","addr":"대구 동구 신천동 478","region":"동구","fid":2},{"num":977,"x":"128.6409923","y":"35.91901765","addr":"대구 동구 봉무동 1561-3","region":"동구","fid":2},{"num":978,"x":"128.6459335","y":"35.91893126","addr":"대구 동구 봉무동 1558","region":"동구","fid":2},{"num":979,"x":"128.644826","y":"35.92028916","addr":"대구 동구 봉무동 1558","region":"동구","fid":2},{"num":980,"x":"128.7468618","y":"35.86862259","addr":"대구 동구 대림동 765","region":"동구","fid":2},{"num":981,"x":"128.6944568","y":"35.86721602","addr":"대구 동구 율하동 1139","region":"동구","fid":2},{"num":982,"x":"128.7031357","y":"35.86963869","addr":"대구 동구 율하동 936","region":"동구","fid":2},{"num":983,"x":"128.6462796","y":"35.93221537","addr":"대구 동구 봉무동 145","region":"동구","fid":2},{"num":984,"x":"128.6381792","y":"35.87443097","addr":"대구 동구 효목동 493-17","region":"동구","fid":2},{"num":985,"x":"128.6244192","y":"35.86893669","addr":"대구 동구 신천동 768-35","region":"동구","fid":2},{"num":986,"x":"128.6330192","y":"35.87332259","addr":"대구 동구 신천동 457","region":"동구","fid":2},{"num":987,"x":"128.6226125","y":"35.86874736","addr":"대구 동구 신천동 850-6","region":"동구","fid":2},{"num":988,"x":"128.6971908","y":"35.93017788","addr":"대구 동구 평광동 1029-1","region":"동구","fid":2},{"num":989,"x":"128.6257844","y":"35.88025403","addr":"대구 동구 신암동 230-7","region":"동구","fid":2},{"num":990,"x":"128.6164534","y":"35.87596136","addr":"대구 동구 신천동 1307-46","region":"동구","fid":2},{"num":991,"x":"128.6384462","y":"35.88662201","addr":"대구 동구 신암동 36-1","region":"동구","fid":2},{"num":992,"x":"128.6373184","y":"35.92758847","addr":"대구 동구 봉무동 1624","region":"동구","fid":2},{"num":993,"x":"128.6494616","y":"35.90997278","addr":"대구 동구 도동 13","region":"동구","fid":2},{"num":994,"x":"128.6480515","y":"35.91434689","addr":"대구 동구 불로동 336-3","region":"동구","fid":2},{"num":995,"x":"128.6326069","y":"35.86835572","addr":"대구 동구 신천동 349-12","region":"동구","fid":2},{"num":996,"x":"128.7217279","y":"35.93393956","addr":"대구 동구 평광동 104","region":"동구","fid":2},{"num":997,"x":"128.7256295","y":"35.93507635","addr":"대구 동구 평광동 산 33","region":"동구","fid":2},{"num":998,"x":"128.7201546","y":"35.93634771","addr":"대구 동구 평광동 산 44","region":"동구","fid":2},{"num":999,"x":"128.7194409","y":"35.93314159","addr":"대구 동구 평광동 146","region":"동구","fid":2}]